Workbook

Sheet LEEME
A1: Cómo usar este archivo
B3: Este archivo es tu lista de artículos candidatos. Tienes 26 artículos para revisar.
B4: Ya está todo pegado. No tienes que pegar ni borrar nada.
A6: 1 | B6: Abre la pestaña "Candidatos". Solo verás tus filas: ya están filtradas para ti.
A7: 2 | B7: En cada fila, escribe Sigue o Sale en las columnas amarillas de la derecha, en este orden: 1. Título, 2. Resumen, 3. Cuartil, 4. Intro y conclusiones, 5. Completo.
A8: 3 | B8: Solo avanzas al siguiente filtro con las filas que dijeron Sigue. Para el cuartil escribes Q1, Q2, Q3, Q4 o No aparece.
A9: 4 | B9: La columna Resultado te dice sola cuáles quedan APROBADO.
A10: 5 | B10: Los artículos APROBADO los copias a tu otro archivo, Matriz_Joaquin.xlsx, hasta completar 12.
B12: IMPORTANTE: no toques la pestaña "Conteo" ni la pestaña "Preseleccionados". Se calculan solas.
B13: AL TERMINAR: devuélvele este archivo a Carlos, junto con Matriz_Joaquin.xlsx, tus PDF y tus capturas de Scimago.

Sheet Candidatos
A1: Trabaja solo tus filas (Asignado = Joaquín). Escribe Sigue o Sale en las columnas amarillas de la derecha.
A2: N.° | B2: Título | C2: Autores | D2: Año | E2: Revista | F2: DOI | G2: Resumen | H2: Base de origen | I2: Control | J2: Asignado | K2: 1. Título | L2: 2. Resumen | M2: 3. Cuartil | N2: 4. Intro y conclusiones | O2: 5. Completo | P2: Resultado | Q2: Afiliación (para el país) | R2: Búsqueda
A3: =IF(B3="","",ROW()-2) | B3: Machine Learning to Enhance the Detection of Terrorist Financing and Suspicious Transactions in Migrant Remittances | C3: Mbiva S.M.; Correa F.M. | D3: 2024 | E3: Journal of Risk and Financial Management | F3: 10.3390/jrfm17050181 | G3: Migrant remittances have become significant in poverty alleviation and microeconomic development in low-income countries. However, the ease of conducting global migrant remittance transfers has also introduced the risk of misuse by terrorist organizations to quickly move and conceal operational funds, facilitating terrorism financing. This study aims to develop an unsupervised machine learning algorithm capable of detecting suspicious financial transactions associated with terrorist financing in migrant remittances. To achieve this goal, a structural equation model (SEM) and an outlier detection algorithm were developed to analyze and identify suspicious transactions among the financial activities of migrants residing in Belgium. The results show that the SEM model classifies a significantly high number of transactions as suspicious, making it prone to detecting false positives. Finally, the study developed an ensemble outlier detection algorithm that comprises an isolation forest (IF) and a local outlier factor (LOF) to detect suspicious transactions in the same dataset. The model performed exceptionally well, being able to detect over 90% of suspicious transactions. © 2024 by the authors. | H3: Scopus | I3: =IF(B3="","",IF(AND(F3<>"",SUMPRODUCT(--ISNUMBER(SEARCH(Preseleccionados!$A$2:$A$11,F3)))>0),"YA ESTÁ",IF(AND(F3<>"",COUNTIF($F$3:F3,F3)>1),"REPETIDO",""))) | J3: =IF(OR(B3="",I3<>""),"",IF(MOD(COUNTIFS($B$3:B3,"<>",$I$3:I3,""),2)=1,"Carlos","Joaquín")) | P3: =IF(J3="","",IF(K3="Sale","Descartado",IF(L3="Sale","Descartado",IF(OR(M3="Q3",M3="Q4",M3="No aparece"),"Descartado",IF(N3="Sale","Descartado",IF(O3="Sigue","APROBADO","En proceso")))))) | Q3: Department of Statistics, Rhodes University, Eastern Cape, Makanda, 6139, South Africa; Department of Mathematical Statistics and Actuarial Sciences, University of the Free State, Bloemfontein, 9302, South Africa | R3: Casas de cambio
A4: =IF(B4="","",ROW()-2) | B4: A Proposed Paradigm Using Data Mining to Minimize Online Money Laundering | C4: Ouf S.; Ashraf M.; Roushdy M. | D4: 2024 | E4: Informatica (Slovenia) | F4: 10.31449/inf.v48i3.6103 | G4: Since the global financial crisis (GFC), banks have been compromised by various risks. One of the significant risks is online money laundering. It is the third-largest business in the world after currency exchange and the automotive industry. As technology has advanced, the methods of online money laundering have become more evasive. Banks' traditional methods cannot deal with online money laundering. The absence of contemporary anti-money laundering techniques has led to the rise of this criminal activity. As a result, the existing systems need effective technology to accommodate the development of online money laundering. Data mining is the technology that applies mathematical, statistical, and machine-learning techniques to extract patterns like malicious behavior of money launderers and gain information about whether the online transaction belongs to money laundering. Many research papers apply different data mining techniques to predict online money laundering. By analyzing these research papers, we found that authors focused on applying one or two data mining techniques to predict online money laundering but ignored combining many techniques like classification, clustering, and association to improve the accuracy of prediction and overcome the limitations of each of them. Therefore, this paper proposes and implements a paradigm (APPD-OML) based on classification, clustering, and association techniques to improve the accuracy of predicting and detecting online money laundering. The result of testing the proposed paradigm illustrates that the prediction and detection of online money laundering based on applying data mining techniques like classification, clustering, and association achieve a strong accuracy of 94%, f-measure of 95%, and AUC 95% which means that the proposed paradigm outperforms each technique used separately in predicting and detecting online money laundering and outperformed the other research that used data mining in this field. © 2024 Slovene Society Informatika. All rights reserved. | H4: Scopus | I4: =IF(B4="","",IF(AND(F4<>"",SUMPRODUCT(--ISNUMBER(SEARCH(Preseleccionados!$A$2:$A$11,F4)))>0),"YA ESTÁ",IF(AND(F4<>"",COUNTIF($F$3:F4,F4)>1),"REPETIDO",""))) | J4: =IF(OR(B4="",I4<>""),"",IF(MOD(COUNTIFS($B$3:B4,"<>",$I$3:I4,""),2)=1,"Carlos","Joaquín")) | K4: Sigue | L4: Sigue | N4: Sale | P4: =IF(J4="","",IF(K4="Sale","Descartado",IF(L4="Sale","Descartado",IF(OR(M4="Q3",M4="Q4",M4="No aparece"),"Descartado",IF(N4="Sale","Descartado",IF(O4="Sigue","APROBADO","En proceso")))))) | Q4: Information Systems Department, Faculty of Commerce and Business Administration, Helwan University, Helwan, Egypt; Faculty of Computers & Information Technology, Future University in Egypt New Cairo, Cairo, Egypt | R4: Casas de cambio
A5: =IF(B5="","",ROW()-2) | B5: Legal and regulatory challenges in addressing high-tech crimes in the banking sector: developing a cybersecurity risk assessment framework for Vietnam | C5: Bui L.V. | D5: 2026 | E5: Journal of Banking Regulation | F5: 10.1057/s41261-025-00302-0 | G5: High-technology crime in the banking sector has become increasingly transnational, data-intensive, and regulation-sensitive, posing challenges that extend beyond technical detection to governance, compliance, and supervisory accountability. While much of the scholarly literature emphasizes machine learning and predictive accuracy, the supervisory value of risk frameworks in emerging markets lies in their ability to remain auditable, law-anchored, and governance-ready. This paper addresses that gap by developing a comprehensive cybersecurity and financial-crime risk-assessment framework tailored to Vietnam’s banking sector. The framework explicitly maps binding regulatory instruments including cybersecurity law, anti-money laundering and counter-terrorist financing (AML/CFT) provisions, and data-governance requirements into operational control criteria with article- and section-level traceability. Risk is systematically organized across three layers: threats and exposures, control systems, and consequences, ensuring both legal coherence and operational applicability. The methodology emphasizes transparency and reproducibility, relying exclusively on public sources such as codified texts, national and cross-border statistics, sectoral incident reporting, and well-documented case studies. Validation is implemented through a three-stage protocol: (i) a Delphi panel to establish expert consensus on domain weights and cutoffs; (ii) inter-rater reliability testing using standardized scenarios to measure scoring consistency; and (iii) sensitivity and stress testing to probe the robustness of results under perturbations of legal salience and corridor exposure. Supplementary case-based scoring of public incidents provides applied demonstrations, reinforcing the framework’s capacity to generate governance-grade insights without reliance on proprietary transaction data. The findings yield a supervision-grade instrument that makes error-cost asymmetries explicit, particularly the higher regulatory cost of false negatives (FN) compared to false positives (FP) in AML/CFT contexts while operationalizing statutory obligations for data localization, third-country transfers, and suspicious transaction reporting. By embedding corridor-specific oversight, explainability artifacts for reviewer workflows, and proportionality mechanisms anchored in public corridor intelligence, the framework equips both banks and regulators with a deployable tool for prioritizing remediation, harmonizing oversight documentation, and preparing for in-country validation within regulatory sandboxes. More broadly, it demonstrates a replicable pathway for emerging markets to align supervisory technology with global standards while preserving transparency, auditability, and contextual sensitivity. © The Author(s) 2026. | H5: Scopus | I5: =IF(B5="","",IF(AND(F5<>"",SUMPRODUCT(--ISNUMBER(SEARCH(Preseleccionados!$A$2:$A$11,F5)))>0),"YA ESTÁ",IF(AND(F5<>"",COUNTIF($F$3:F5,F5)>1),"REPETIDO",""))) | J5: =IF(OR(B5="",I5<>""),"",IF(MOD(COUNTIFS($B$3:B5,"<>",$I$3:I5,""),2)=1,"Carlos","Joaquín")) | P5: =IF(J5="","",IF(K5="Sale","Descartado",IF(L5="Sale","Descartado",IF(OR(M5="Q3",M5="Q4",M5="No aparece"),"Descartado",IF(N5="Sale","Descartado",IF(O5="Sigue","APROBADO","En proceso")))))) | Q5: Bristol Law School, University of the West of England, Bristol, United Kingdom; International School, Vietnam National University, Hanoi, Viet Nam | R5: Bancos
A6: =IF(B6="","",ROW()-2) | B6: The Imbalanced Classification of Fraudulent Bank Transactions Using Machine Learning | C6: Ruchay A.; Feldman E.; Cherbadzhi D.; Sokolov A. | D6: 2023 | E6: Mathematics | F6: 10.3390/math11132862 | G6: This article studies the development of a reliable AI model to detect fraudulent bank transactions, including money laundering, and illegal activities with goods and services. The proposed machine learning model uses the CreditCardFraud dataset and utilizes multiple algorithms with different parameters. The results are evaluated using Accuracy, Precision, Recall, F1 score, and IBA. We have increased the reliability of the imbalanced classification of fraudulent credit card transactions in comparison to the best known results by using the Tomek links resampling algorithm of the imbalanced CreditCardFraud dataset. The reliability of the results, using the proposed model based on the TPOT and RandomForest algorithms, has been confirmed by using 10-fold cross-validation. It is shown that on the dataset the accuracy of the proposed model detecting fraudulent bank transactions reaches 99.99%. © 2023 by the authors. | H6: Scopus | I6: =IF(B6="","",IF(AND(F6<>"",SUMPRODUCT(--ISNUMBER(SEARCH(Preseleccionados!$A$2:$A$11,F6)))>0),"YA ESTÁ",IF(AND(F6<>"",COUNTIF($F$3:F6,F6)>1),"REPETIDO",""))) | J6: =IF(OR(B6="",I6<>""),"",IF(MOD(COUNTIFS($B$3:B6,"<>",$I$3:I6,""),2)=1,"Carlos","Joaquín")) | K6: Sigue | L6: Sigue | N6: Sale | P6: =IF(J6="","",IF(K6="Sale","Descartado",IF(L6="Sale","Descartado",IF(OR(M6="Q3",M6="Q4",M6="No aparece"),"Descartado",IF(N6="Sale","Descartado",IF(O6="Sigue","APROBADO","En proceso")))))) | Q6: Department of Information Security, South Ural State University (National Research University), Chelyabinsk, 454080, Russian Federation; Department of Mathematics, Chelyabinsk State University, Chelyabinsk, 454001, Russian Federation | R6: Bancos
A7: =IF(B7="","",ROW()-2) | B7: Explainable deep learning model for predicting money laundering transactions | C7: Kute D.V.; Pradhan B.; Shukla N.; Alamri A. | D7: 2024 | E7: International Journal on Smart Sensing and Intelligent Systems | F7: 10.2478/ijssis-2024-0027 | G7: Money laundering has been a global issue for decades. The ever-changing technology landscape, digital channels, and regulations make it increasingly difficult. Financial institutions use rule-based systems to detect suspicious money laundering transactions. However, it suffers from large false positives (FPs) that lead to operational efforts or misses on true positives (TPs) that increase the compliance risk. This paper presents a study of convolutional neural network (CNN) to predict money laundering and employs SHapley Additive exPlanations (SHAP) explainable artificial intelligence (AI) method to explain the CNN predictions. The results highlight the role of CNN in detecting suspicious transactions with high accuracy and SHAP’s role in bringing out the rationale of deep learning predictions. © 2024 Kute et al. | H7: Scopus | I7: =IF(B7="","",IF(AND(F7<>"",SUMPRODUCT(--ISNUMBER(SEARCH(Preseleccionados!$A$2:$A$11,F7)))>0),"YA ESTÁ",IF(AND(F7<>"",COUNTIF($F$3:F7,F7)>1),"REPETIDO",""))) | J7: =IF(OR(B7="",I7<>""),"",IF(MOD(COUNTIFS($B$3:B7,"<>",$I$3:I7,""),2)=1,"Carlos","Joaquín")) | P7: =IF(J7="","",IF(K7="Sale","Descartado",IF(L7="Sale","Descartado",IF(OR(M7="Q3",M7="Q4",M7="No aparece"),"Descartado",IF(N7="Sale","Descartado",IF(O7="Sigue","APROBADO","En proceso")))))) | Q7: Centre for Advanced Modelling and Geospatial Information Systems (CAMGIS), Faculty of Engineering and Information Technology, University of Technology Sydney, Sydney, 2007, NSW, Australia; Department of Business Strategy and Innovation, Griffith Business School, Griffith University, Brisbane, 4111, QLD, Australia; Department of Geology and Geophysics, College of Science, King Saud University, Riyadh, 11451, Saudi Arabia | R7: Bancos
A8: =IF(B8="","",ROW()-2) | B8: Anti-money laundering powered by graph machine learning: 'Show me your friends and I will tell you who you are' | C8: Astrova I. | D8: 2023 | E8: Intelligent Decision Technologies | F8: 10.3233/IDT-220193 | G8: Today financial institutions have been investing billions of US dollars to detect money laundering. When financial institutions are found to have their customers conduct money laundering through them, they are subjected to large penalties. Moreover, their reputation suffers greatly through public exposure. In response, financial institutions have been exploring opportunities to use graph machine learning algorithms. This paper describes one of those algorithms called Anti-TrustRank and demonstrates how it can be used to identify money launderers. In contrast to many other algorithms, Anti-TrustRank calls for selecting a very small set of customers to be confirmed by human experts (e.g., compliance officers or analysts) as money launderers. Once this set has been identified, Anti-TrustRank seeks out customers linked (either directly or indirectly) to those money launderers. © 2023 - IOS Press. All rights reserved. | H8: Scopus | I8: =IF(B8="","",IF(AND(F8<>"",SUMPRODUCT(--ISNUMBER(SEARCH(Preseleccionados!$A$2:$A$11,F8)))>0),"YA ESTÁ",IF(AND(F8<>"",COUNTIF($F$3:F8,F8)>1),"REPETIDO",""))) | J8: =IF(OR(B8="",I8<>""),"",IF(MOD(COUNTIFS($B$3:B8,"<>",$I$3:I8,""),2)=1,"Carlos","Joaquín")) | K8: Sigue | L8: Sigue | P8: =IF(J8="","",IF(K8="Sale","Descartado",IF(L8="Sale","Descartado",IF(OR(M8="Q3",M8="Q4",M8="No aparece"),"Descartado",IF(N8="Sale","Descartado",IF(O8="Sigue","APROBADO","En proceso")))))) | Q8: Applied Artificial Intelligence Group, Department of Software Science, Tallinn University of Technology, Akadeemia tee 21, Tallinn, 12618, Estonia | R8: Bancos
A9: =IF(B9="","",ROW()-2) | B9: AI culture ‘profiling’ and anti-money laundering: Efficacy vs ethics | C9: Goodell J.W.; Muckley C.B.; Neelakantan P.; Ryan D.; Yu P.-S. | D9: 2025 | E9: International Review of Financial Analysis | F9: 10.1016/j.irfa.2025.103980 | G9: Using extensive transaction and money laundering detection data, at a globally important financial institution, we investigate the efficacy of including facets of national culture in formulating anti-money laundering predictions. For corporate and individual accounts, Hofstede individualism scores of the country in which a customer is resident, or from which a wire is sent/received, are of first-order importance in the detection of money laundering. When combined with account and transaction data; as well as even a proprietary institutional algorithm, individualism scores continue to determine the models’ predictive performances. The efficacy of cultural profiling in money laundering detection underscores the need for stringent and enforced data protection to prohibit its use. This will safeguard the civil right of individuals to privacy and promote financial inclusion. © 2025 Elsevier Inc. | H9: Scopus | I9: =IF(B9="","",IF(AND(F9<>"",SUMPRODUCT(--ISNUMBER(SEARCH(Preseleccionados!$A$2:$A$11,F9)))>0),"YA ESTÁ",IF(AND(F9<>"",COUNTIF($F$3:F9,F9)>1),"REPETIDO",""))) | J9: =IF(OR(B9="",I9<>""),"",IF(MOD(COUNTIFS($B$3:B9,"<>",$I$3:I9,""),2)=1,"Carlos","Joaquín")) | P9: =IF(J9="","",IF(K9="Sale","Descartado",IF(L9="Sale","Descartado",IF(OR(M9="Q3",M9="Q4",M9="No aparece"),"Descartado",IF(N9="Sale","Descartado",IF(O9="Sigue","APROBADO","En proceso")))))) | Q9: The University of Akron, Akron, OH, United States; Smurfit Graduate School of Business and Geary Institute, University College Dublin, Ireland; Indian Institute of Technology Kanpur, India; NCLA, Physics, School of Natural Sciences, University of Galway, Ireland | R9: Bancos
A10: =IF(B10="","",ROW()-2) | B10: Predicting money laundering sanctions using machine learning algorithms and artificial neural networks | C10: Lokanan M.E. | D10: 2024 | E10: Applied Economics Letters | F10: 10.1080/13504851.2023.2176435 | G10: This article used machine learning (ML) and artificial neural network (ANN) algorithms to predict the likelihood of a country being sanctioned by the Basel Institute on Governance for not adhering to anti-money laundering (AML) standards. Data for this paper came from the Basel AML Index and the World Bank. The results showed that the logistic regression and support vector machine (SVM) classifiers had the highest performance and balanced accuracy scores in sanction prediction. Additionally, these two algorithms also had the highest precision, specificity, and F1 scores, indicating that they were robust in their predictions of money laundering sanctions. In contrast to the ML classifiers, the ANN model had the highest sensitivity and receiver operating characteristic scores for money laundering sanctions. The strongest predictors of sanctions are financial transparency, political and legal risks, unemployment rate, and money laundering and terrorist financing risks. These findings reinforce the potential practical applications of ML and ANN models in predicting sanctions. © 2023 Informa UK Limited, trading as Taylor & Francis Group. | H10: Scopus | I10: =IF(B10="","",IF(AND(F10<>"",SUMPRODUCT(--ISNUMBER(SEARCH(Preseleccionados!$A$2:$A$11,F10)))>0),"YA ESTÁ",IF(AND(F10<>"",COUNTIF($F$3:F10,F10)>1),"REPETIDO",""))) | J10: =IF(OR(B10="",I10<>""),"",IF(MOD(COUNTIFS($B$3:B10,"<>",$I$3:I10,""),2)=1,"Carlos","Joaquín")) | K10: Sigue | L10: Sale | P10: =IF(J10="","",IF(K10="Sale","Descartado",IF(L10="Sale","Descartado",IF(OR(M10="Q3",M10="Q4",M10="No aparece"),"Descartado",IF(N10="Sale","Descartado",IF(O10="Sigue","APROBADO","En proceso")))))) | Q10: Faculty of Management, Royal Roads University, Victoria, BC, Canada | R10: Bancos
A11: =IF(B11="","",ROW()-2) | B11: Optimization of Deep Learning-Based Model for Identification of Credit Card Frauds | C11: Palivela H.; Rishiwal V.; Bhushan S.; Alotaibi A.; Agarwal U.; Kumar P.; Yadav M. | D11: 2024 | E11: IEEE Access | F11: 10.1109/ACCESS.2024.3440637 | G11: With the growth of the internet, the landscape of commercial transactions has undergone significant changes. The digital revolution has permeated various aspects of our daily lives, notably transforming the financial system through digital money transfers across global distances. Digital transactions, including online purchases, money transfers, banking, and investing, have become routine. This shift has provided many advantages and opened the door for illegal activities such as money laundering. This research aims to identify transaction patterns to help algorithms recognize and flag scammers. We propose a deep learning-based sequential model framework to optimize fraud and non-fraud transaction classification. Proposed approach incorporates methods of ensemble learning including Gradient Boost, Random Forest, Logistic Regression, and Voting Classifiers, along with hyperparameter tuning to prevent overfitting. To solve the dataset inconsistency common in credit card dataset, we used techniques like under-sampling and the Synthetic Minority Over-sampling Technique (SMOTE) with specific machine learning (ML) algorithms. Our methodology involves data pre-processing, feature engineering, model selection, and evaluation. We leveraged the computational power of Google Colab for efficient model training and testing. Temporal features were extracted to capture transaction patterns over time, such as frequency and timing, along with features based on transaction amounts, merchant types, and geographic locations to detect subtle anomalies indicative of fraud. These features were input into a supervised learning algorithm, resulting in a model significantly outperforming baseline methods. The model was tested using a sizable dataset of anonymized transactions made with credit cards, and its effectiveness was measured using metrics such as accuracy, precision, recall, and F1-score. While it cannot entirely prevent fraudulent transactions, it effectively manages false positives through careful review, achieving an accuracy of 99.59%, surpassing other innovative models. © 2013 IEEE. | H11: Scopus | I11: =IF(B11="","",IF(AND(F11<>"",SUMPRODUCT(--ISNUMBER(SEARCH(Preseleccionados!$A$2:$A$11,F11)))>0),"YA ESTÁ",IF(AND(F11<>"",COUNTIF($F$3:F11,F11)>1),"REPETIDO",""))) | J11: =IF(OR(B11="",I11<>""),"",IF(MOD(COUNTIFS($B$3:B11,"<>",$I$3:I11,""),2)=1,"Carlos","Joaquín")) | P11: =IF(J11="","",IF(K11="Sale","Descartado",IF(L11="Sale","Descartado",IF(OR(M11="Q3",M11="Q4",M11="No aparece"),"Descartado",IF(N11="Sale","Descartado",IF(O11="Sigue","APROBADO","En proceso")))))) | Q11: Damac Properties, LLC, Dubai, United Arab Emirates; M.J.P. Rohilkhand University, Department of CSIT, Bareilly, 243006, India; Universiti Teknologi PETRONAS, Department of CIS, Perak, Seri Iskandar, 32160, Malaysia; Taif University, College of Computers and Information Technology, Department of Computer Science, Taif, 26571, Saudi Arabia; RBMI Group of Institutions, Department of CSIT, Bareilly, 224001, India; Swami Rama Himalayan University, Department of Computer Science and Engineering, Dehradun, 248016, India; Bareilly College, Department of Computer Science, Bareilly, 243001, India | R11: Bancos
A12: =IF(B12="","",ROW()-2) | B12: The importance of governance in artificial intelligence and machine learning technology | C12: Chieng S.; Dasgupta S. | D12: 2025 | E12: Journal of Financial Compliance | F12: 10.69554/PKAQ4460 | G12: Financial institutions increasingly deploy artificial intelligence (AI) and machine learning (ML) solutions to enhance compliance processes. While this trend promises significant efficiency gains, it also introduces complex governance challenges that compliance executives must effectively address. Drawing on regulatory developments, technical considerations and industry best practices, this paper presents the process to develop a comprehensive governance framework for mitigating risks associated with AI/ ML implementation in compliance functions. This paper concludes with a forward-looking perspective on evolving governance requirements as AI/ML technologies continue to transform financial compliance. This article is also included in The Business & Management Collection which can be accessed at https://hstalks.com/business/. © Henry Stewart Publications. | H12: Scopus | I12: =IF(B12="","",IF(AND(F12<>"",SUMPRODUCT(--ISNUMBER(SEARCH(Preseleccionados!$A$2:$A$11,F12)))>0),"YA ESTÁ",IF(AND(F12<>"",COUNTIF($F$3:F12,F12)>1),"REPETIDO",""))) | J12: =IF(OR(B12="",I12<>""),"",IF(MOD(COUNTIFS($B$3:B12,"<>",$I$3:I12,""),2)=1,"Carlos","Joaquín")) | K12: Sale | P12: =IF(J12="","",IF(K12="Sale","Descartado",IF(L12="Sale","Descartado",IF(OR(M12="Q3",M12="Q4",M12="No aparece"),"Descartado",IF(N12="Sale","Descartado",IF(O12="Sigue","APROBADO","En proceso")))))) | Q12: Interactive Brokers, One Pickwick Plaza, Greenwich, 06830, CT, United States | R12: Bancos
A13: =IF(B13="","",ROW()-2) | B13: Comparative analysis of machine learning algorithms for money laundering detection | C13: Ajagbe S.A.; Majola S.; Mudali P. | D13: 2025 | E13: Discover Artificial Intelligence | F13: 10.1007/s44163-025-00397-4 | G13: This study explored the effectiveness of anomaly detection techniques in identifying fraudulent financial transactions, with a particular focus on money laundering activities. The research addressed the growing challenges of financial fraud, which significantly impacts economies and financial institutions by leading to substantial monetary losses and undermining trust in financial systems. This research examined contemporary machine learning (ML) algorithms, including XGBoost, K-Nearest Neighbors, Random Forest, Isolation Forest, and Support Vector Machines, to analyze transaction data for anomalies indicative of fraudulent behavior. This study’s approach involves data collecting, system design, implementation, data analysis, and experimental setup. This research aimed to identify robust algorithms for detecting financial fraud. In the results notably, XGBoost shows an output of 1.0, 1.0, 1.0, 1.0, and 0.94 for accuracy, precision, recall, F1 score and AUC respectively to outperform other ML algorithms experimented in money laundering detection. The findings underscore the potential of ML algorithms capability to combat money laundering and indeed enhance anti-money efforts and offer financial institutions a powerful, resource-efficient method for fraud detection in large-scale transaction environments. © The Author(s) 2025. | H13: Scopus | I13: =IF(B13="","",IF(AND(F13<>"",SUMPRODUCT(--ISNUMBER(SEARCH(Preseleccionados!$A$2:$A$11,F13)))>0),"YA ESTÁ",IF(AND(F13<>"",COUNTIF($F$3:F13,F13)>1),"REPETIDO",""))) | J13: =IF(OR(B13="",I13<>""),"",IF(MOD(COUNTIFS($B$3:B13,"<>",$I$3:I13,""),2)=1,"Carlos","Joaquín")) | P13: =IF(J13="","",IF(K13="Sale","Descartado",IF(L13="Sale","Descartado",IF(OR(M13="Q3",M13="Q4",M13="No aparece"),"Descartado",IF(N13="Sale","Descartado",IF(O13="Sigue","APROBADO","En proceso")))))) | Q13: Department of Computer Science, University of Zululand, KZN, Kwadlangezwa, 3886, South Africa; Department of Computer Engineering, Abiola Ajimobi Technical University, Ibadan, 200255, Nigeria | R13: Bancos
A14: =IF(B14="","",ROW()-2) | B14: Scalable Community-Enriched Graph Representation Learning for Group-Level Anomaly Detection in Financial Transactions | C14: Nourollah Z.; Rezvani M.; Zahedi M. | D14: 2027 | E14: International Journal of Engineering, Transactions A: Basics | F14: 10.5829/ije.2027.40.03c.10 | G14: Identifying suspicious subnetworks in financial transaction systems is crucial for preventing fraud and mitigating institutional risks. However, detecting organized illicit activities remains challenging because of evolving network structures and sophisticated concealment strategies that intentionally obscure connectivity to bypass topology-driven detection. This study presents FinCEG-Net, a scalable framework for group-level anomaly detection. It comprises three stages: (1) Transaction Graph Construction, modeling monetary flows as a directed attributed graph; (2) Community-Enriched Graph Representation Learning, where graph representation learning is employed to estimate semantic edge affinities that guide community structuring. This process enables the discovery of latent illicit structures, which are groups that are topologically sparse yet behaviorally cohesive, thereby mitigating structural bias in density-driven clustering. The representation is further enriched through an Institution-Enriched Group Graph (IEGG), which integrates interbank relationships to enhance cross-institution information propagation. (3) Suspicious Subnetwork Detection, where a supervised classifier fuses multimodal representations to identify high-risk transaction groups in batch and near-real-time settings. Experiments on real-world datasets from an Iranian bank and Romania's Libra Internet Bank demonstrated that FinCEG-Net consistently outperformed the baseline models, achieving substantial improvements in PRAUC, precision, recall, and F1-score. These results highlight the effectiveness of the proposed framework in identifying suspicious transaction groups in the real world. © 2027 The author(s). This is an open access article distributed under the terms of the Creative Commons Attribution (CC BY 4.0), which permits unrestricted use, distribution, and reproduction in any medium, as long as the original authors and source are cited. No permission is required from the authors or the publishers. | H14: Scopus | I14: =IF(B14="","",IF(AND(F14<>"",SUMPRODUCT(--ISNUMBER(SEARCH(Preseleccionados!$A$2:$A$11,F14)))>0),"YA ESTÁ",IF(AND(F14<>"",COUNTIF($F$3:F14,F14)>1),"REPETIDO",""))) | J14: =IF(OR(B14="",I14<>""),"",IF(MOD(COUNTIFS($B$3:B14,"<>",$I$3:I14,""),2)=1,"Carlos","Joaquín")) | P14: =IF(J14="","",IF(K14="Sale","Descartado",IF(L14="Sale","Descartado",IF(OR(M14="Q3",M14="Q4",M14="No aparece"),"Descartado",IF(N14="Sale","Descartado",IF(O14="Sigue","APROBADO","En proceso")))))) | Q14: Faculty of Computer Engineering, Shahrood University of Technology, Shahrood, Iran | R14: Bancos
A15: =IF(B15="","",ROW()-2) | B15: Hybrid deep learning for anti-money laundering: Unsupervised detection of emerging schemes via feature fusion and explainable artificial intelligence | C15: Kungu C.O.; Senagi K.; Omondi E. | D15: 2026 | E15: Machine Learning with Applications | F15: 10.1016/j.mlwa.2026.100856 | G15: Traditional rule-based anti-money laundering (AML) transaction monitoring systems suffer from high false-positive rates and rigidity in detecting complex emerging risk. This limitation has prompted changes to the Financial Action Task Force (FATF) recommendation 16, mandating the use of advanced systems for detecting money laundering schemes in cross-border payments. This study developed a hybrid framework integrating VAE-learned behavioural latent factors, GNN-captured relational network signals, and rule-based heuristics for enhanced anomaly detection. The model was evaluated on 54,258 real-world cross-border transaction records from an East African commercial bank. The One-Class SVM, optimised via a rigorous grid search proved superior compared to Isolation Forest and Local Outlier Factor benchmark, achieving a precision of 99.63% in the top 5% of prioritised alerts. Independent validation by a Kenyan financial institution confirms a batch processing speed of 1000 transactions per second on standard computer hardware (Intel Core i7, 16 GB RAM) and efficient high-priority alert triage, key requirements for deployment in financial institutions. Shapley additive explanations analysis further provided the interpretability of the feature contribution to the model performance. These results demonstrated that integration of rule-based features with deep-learning embeddings improves compliance work efficiency and proven pathway for resource-constrained financial institutions to comply with FATF regulatory demands upcoming in 2030. © 2026 The Authors. | H15: Scopus | I15: =IF(B15="","",IF(AND(F15<>"",SUMPRODUCT(--ISNUMBER(SEARCH(Preseleccionados!$A$2:$A$11,F15)))>0),"YA ESTÁ",IF(AND(F15<>"",COUNTIF($F$3:F15,F15)>1),"REPETIDO",""))) | J15: =IF(OR(B15="",I15<>""),"",IF(MOD(COUNTIFS($B$3:B15,"<>",$I$3:I15,""),2)=1,"Carlos","Joaquín")) | K15: Sale | P15: =IF(J15="","",IF(K15="Sale","Descartado",IF(L15="Sale","Descartado",IF(OR(M15="Q3",M15="Q4",M15="No aparece"),"Descartado",IF(N15="Sale","Descartado",IF(O15="Sigue","APROBADO","En proceso")))))) | Q15: Institute of Mathematical Sciences, Strathmore University, P.O. Box 59857-00200, Nairobi, Kenya; @ilabAfrica, Strathmore University, P.O. Box 59857-00200, Nairobi, Kenya; International Centre of Insect Physiology and Ecology, Duduville Campus, off Thika Road, Kasarani, P.O. Box 30772-00100, Nairobi, Kenya; African Population and Health Research Center, P.O. Box 10787-00100, Nairobi, Kenya | R15: Bancos
A16: =IF(B16="","",ROW()-2) | B16: Developing a scoring model for managing money laundering transactions using machine learning | C16: Halford E.; Gibson I.; Newfield M.; Dhanwala M. | D16: 2025 | E16: Journal of Money Laundering Control | F16: 10.1108/JMLC-09-2024-0152 | G16: Purpose: The purpose of this study is twofold. Firstly, this study outlines the creation of an ML “bolt on” transaction monitoring risk scoring model. This ML model uses predictive classification to score the likelihood of an alert being a false or true positive based on historical data. Secondly, this study explores the results of implementing the model in a real-world environment. This is valuable, as it explores the potential to reduce the workload on human analysts responsible for reviewing alerts, by “hibernating” low-risk alerts and “auto-escalating” high-risk alerts. Design/methodology/approach: Machine learning is used to create a “bolt on” model that sits on top of existing rule-based transaction monitoring systems to improve their effectiveness and efficiency. This was achieved by developing a model to mimic the analysts alert review process with the aim of improving efficiency, reducing investigation timeliness and ultimately reducing time-to-SAR duration. The model did so by scoring anti-money laundering (AML) alerts to help conduct three actions: automatic hibernation of low-risk alerts; review of medium-risk alerts by the level 1 team; and auto-escalation of high-risk alerts to the level 2 team for detailed investigation. Findings: The model was successful in consistently identifying low-risk alerts correctly, significantly reducing the volume of false positives that needed manual review. Prior to implementation, 100% of alerts had to be reviewed, by the end of the examined period, 19% of alerts were hibernated and 18% of alerts were auto-escalated. Time taken to investigate and submit SARs was reduced by 61%. Practical implications: The practical implications of the study lie in its contributions to helping banking institutions effectively keep pace with the increasing volume of transactions, in a cost effective and efficient manner, which has a positive effect on their reputation through enhancing their AML response. Social implications: The model outlined greatly enhances the timeliness of investigations, which is crucial for money laundering prevention and enables timely responses by institutions and law enforcement agencies to make better use of the investigation timeframe after an offence is identified, enabling them to more rapidly address threats, freeze assets when necessary, and secure vital evidence before it is lost. Originality/value: This study provides a blueprint for other financial institutions to consider similar approaches to AML. This is significant because previous studies of machine learning applications in the domain of AML have not explored this type of use before, particularly in the context of machine learning ensembled techniques. It also addressed several cited limitations of previous research by increasing the depth of information in the datasets used and providing a formal evaluation. Importantly, the blueprint and evaluation metrics used in this study ensure its reproducibility, addressing another previously identified academic issue. © 2025, Eric Halford, Ian Gibson, Mark Newfield and Mufazzal Dhanwala. | H16: Scopus | I16: =IF(B16="","",IF(AND(F16<>"",SUMPRODUCT(--ISNUMBER(SEARCH(Preseleccionados!$A$2:$A$11,F16)))>0),"YA ESTÁ",IF(AND(F16<>"",COUNTIF($F$3:F16,F16)>1),"REPETIDO",""))) | J16: =IF(OR(B16="",I16<>""),"",IF(MOD(COUNTIFS($B$3:B16,"<>",$I$3:I16,""),2)=1,"Carlos","Joaquín")) | P16: =IF(J16="","",IF(K16="Sale","Descartado",IF(L16="Sale","Descartado",IF(OR(M16="Q3",M16="Q4",M16="No aparece"),"Descartado",IF(N16="Sale","Descartado",IF(O16="Sigue","APROBADO","En proceso")))))) | Q16: Department of Research and Innovation, Rabdan Academy, Abu Dhabi, United Arab Emirates | R16: Bancos
A17: =IF(B17="","",ROW()-2) | B17: Leveraging artificial intelligence for enhanced anti-money laundering in financial institutions | C17: Premkumar A.; Vidyavathi K.; Sowmya V.L.; Alfurhood B.S.; Irudayasamy A.; Natarajan R. | D17: 2026 | E17: Discover Computing | F17: 10.1007/s10791-026-10142-9 | G17: Financial institutions continue to face a significant challenge with money laundering and need intelligent, scalable ways to detect illegal financial activity. This paper introduces a machine learning-driven platform for detecting suspicious financial activities in transactional data with a fixed schema, enriched with temporal, behavioral, and financial profile features. Extensive experiments were performed with several popular supervised learning algorithms, including Logistic regression, Decision tree, Random Forest, Gradient Boosting, AdaBoost, K-Nearest Neighbour (KNN), Support vector machine, and Naïve Bayes. The Gradient Boosting classifier performed best overall, achieving an Accuracy of 90.59%, a precision of 90.61%, a recall of 90.59%, and an F1-score of 90.60 in balanced detection, with the highest reliability for detecting suspicious financial transactions. It showed better generalization and robust classification performance than the other models, especially in real anti-money laundering problems, where it performed excellently. These results demonstrate that recent artificial intelligence could fortify anti-money laundering systems by automating and improving the detection of high-risk financial activity. The framework provides a scalable and feasible approach to ensure compliance, manage risk, and secure finances for larger organizations. © The Author(s) 2026. | H17: Scopus | I17: =IF(B17="","",IF(AND(F17<>"",SUMPRODUCT(--ISNUMBER(SEARCH(Preseleccionados!$A$2:$A$11,F17)))>0),"YA ESTÁ",IF(AND(F17<>"",COUNTIF($F$3:F17,F17)>1),"REPETIDO",""))) | J17: =IF(OR(B17="",I17<>""),"",IF(MOD(COUNTIFS($B$3:B17,"<>",$I$3:I17,""),2)=1,"Carlos","Joaquín")) | P17: =IF(J17="","",IF(K17="Sale","Descartado",IF(L17="Sale","Descartado",IF(OR(M17="Q3",M17="Q4",M17="No aparece"),"Descartado",IF(N17="Sale","Descartado",IF(O17="Sigue","APROBADO","En proceso")))))) | Q17: Manipal Institute of Technology Bengaluru, Manipal Academy of Higher Education, Manipal, India; Electronics and Communication Engineering Department, Selvam College of Technology, Salem Road (NH44), Pappinaickenpatti (post), Tamil Nadu, Namakkal, 637003, India; Department of Artificial Intelligence and Machine Learning, BMS Institute of Technology & Management, Bengaluru, 560119, India; Department of Computer Sciences, College of Computer and Information Sciences, Princess Nourah bint Abdulrahman University, P.O. Box 84428, Riyadh, 11671, Saudi Arabia; Department of Computing and Information Sciences, College of Computing and Information Sciences, University of Technology and Applied Sciences, Nizwa, 611, Oman; Department of Computing and Information Sciences, College of Computing and Information Sciences, University of Technology and Applied Sciences, AI-Aqr, Shinas, 324, Oman | R17: Bancos
A18: =IF(B18="","",ROW()-2) | B18: A Proposed Paradigm Using Data Mining to Minimize Online Money Laundering | C18: Ouf S.; Ashraf M.; Roushdy M. | D18: 2024 | E18: Informatica (Slovenia) | F18: 10.31449/inf.v48i3.6103 | G18: Since the global financial crisis (GFC), banks have been compromised by various risks. One of the significant risks is online money laundering. It is the third-largest business in the world after currency exchange and the automotive industry. As technology has advanced, the methods of online money laundering have become more evasive. Banks' traditional methods cannot deal with online money laundering. The absence of contemporary anti-money laundering techniques has led to the rise of this criminal activity. As a result, the existing systems need effective technology to accommodate the development of online money laundering. Data mining is the technology that applies mathematical, statistical, and machine-learning techniques to extract patterns like malicious behavior of money launderers and gain information about whether the online transaction belongs to money laundering. Many research papers apply different data mining techniques to predict online money laundering. By analyzing these research papers, we found that authors focused on applying one or two data mining techniques to predict online money laundering but ignored combining many techniques like classification, clustering, and association to improve the accuracy of prediction and overcome the limitations of each of them. Therefore, this paper proposes and implements a paradigm (APPD-OML) based on classification, clustering, and association techniques to improve the accuracy of predicting and detecting online money laundering. The result of testing the proposed paradigm illustrates that the prediction and detection of online money laundering based on applying data mining techniques like classification, clustering, and association achieve a strong accuracy of 94%, f-measure of 95%, and AUC 95% which means that the proposed paradigm outperforms each technique used separately in predicting and detecting online money laundering and outperformed the other research that used data mining in this field. © 2024 Slovene Society Informatika. All rights reserved. | H18: Scopus | I18: =IF(B18="","",IF(AND(F18<>"",SUMPRODUCT(--ISNUMBER(SEARCH(Preseleccionados!$A$2:$A$11,F18)))>0),"YA ESTÁ",IF(AND(F18<>"",COUNTIF($F$3:F18,F18)>1),"REPETIDO",""))) | J18: =IF(OR(B18="",I18<>""),"",IF(MOD(COUNTIFS($B$3:B18,"<>",$I$3:I18,""),2)=1,"Carlos","Joaquín")) | P18: =IF(J18="","",IF(K18="Sale","Descartado",IF(L18="Sale","Descartado",IF(OR(M18="Q3",M18="Q4",M18="No aparece"),"Descartado",IF(N18="Sale","Descartado",IF(O18="Sigue","APROBADO","En proceso")))))) | Q18: Information Systems Department, Faculty of Commerce and Business Administration, Helwan University, Helwan, Egypt; Faculty of Computers & Information Technology, Future University in Egypt New Cairo, Cairo, Egypt | R18: Bancos
A19: =IF(B19="","",ROW()-2) | B19: GCF-MLD: Integrated Approach for Money Laundering Detection Using Machine Learning and Graph Network Analysis | C19: Irshad F.; Alkhalifah T.; Alturise F.; Khan Y.D. | D19: 2024 | E19: IEEE Access | F19: 10.1109/ACCESS.2024.3510115 | G19: Money laundering is a critical issue for financial institutions especially in developing countries and detecting such suspicious activities is a challenging task. The rule-based money laundering detection systems currently being used by the financial institutions rely on pre-defined rules that are often not able to keep up with rapidly changing tactics of money launderers. In this regard, machine learning based approaches have gained attention for detecting suspicious transactions related to money laundering. In this study, we propose a novel approach "Graph-Clustering Fusion for Money Laundering Detection (GCF-MLD)"combining graph network analysis with clustering methodology to identify suspicious accounts in real-world banking dataset. The results exhibit that the proposed model can be effectively used by the financial institutions to replace current rule-based techniques to significantly improve the efficiency and effectiveness of money laundering detection systems. © 2013 IEEE. | H19: Scopus | I19: =IF(B19="","",IF(AND(F19<>"",SUMPRODUCT(--ISNUMBER(SEARCH(Preseleccionados!$A$2:$A$11,F19)))>0),"YA ESTÁ",IF(AND(F19<>"",COUNTIF($F$3:F19,F19)>1),"REPETIDO",""))) | J19: =IF(OR(B19="",I19<>""),"",IF(MOD(COUNTIFS($B$3:B19,"<>",$I$3:I19,""),2)=1,"Carlos","Joaquín")) | K19: Sigue | L19: Sigue | P19: =IF(J19="","",IF(K19="Sale","Descartado",IF(L19="Sale","Descartado",IF(OR(M19="Q3",M19="Q4",M19="No aparece"),"Descartado",IF(N19="Sale","Descartado",IF(O19="Sigue","APROBADO","En proceso")))))) | Q19: University of Management and Technology, School of Systems and Technology, Department of Computer Science, Lahore, 54770, Pakistan; Qassim University, College of Computer, Department of Computer Engineering, Buraydah, 52571, Saudi Arabia; Qassim University, College of Computer, Department of Cybersecurity, Buraydah, 52571, Saudi Arabia | R19: Bancos
A20: =IF(B20="","",ROW()-2) | B20: Scalable Semi-Supervised Graph Learning Techniques for Anti Money Laundering | C20: Karim M.R.; Hermsen F.; Chala S.A.; De Perthuis P.; Mandal A. | D20: 2024 | E20: IEEE Access | F20: 10.1109/ACCESS.2024.3383784 | G20: Money laundering is the process by which criminals move large sums of illicit money to hidden locations and integrate them as legal funds through existing financial services. The United Nations (UN) estimates that 2 to 5% of global GDP, which is approximately 0.8 to 2.0 trillion dollars, is laundered globally every year. Therefore, accurately identifying such globally alarming activities is crucial for enforcing anti-money laundering (AML) measures. Numerous techniques have been proposed to detect money laundering from transaction graphs of money transfers between bank accounts by analysing the structural and behavioural dynamics of their corresponding dense subgraphs. However, these techniques often do not consider that money laundering usually involves high-volume flows of funds through chains of bank accounts. Moreover, most AML approaches either result in lower detection accuracy or incur higher computational costs, making them less reliable and suitable for real financial systems. Consequently, only a fraction of money laundering activities can be detected and prevented. In this paper, we propose an efficient approach to AML by employing semi-supervised graph learning techniques on a large-scale financial transactional graph in both pipeline settings (i.e., graph embedding models are first trained to generate node embeddings that are combined with additional topological graph features to train binary classifiers) and end-to-end settings (i.e., node classification is performed by training SkipGCN, FastGCN, and EvolveGCN without requiring separate classifiers) to identify nodes involved in potential money laundering activities. We evaluate our approach on four datasets: AMLSim, Elliptic, IBM AML, and SynthAML, with a view to scalability and practicality for real financial systems. Further, we provide local (e.g., how money is laundered between nodes) and global (e.g., what factors contribute to money laundering) explanations of the predictions by highlighting the predominant factors in money laundering cases and elucidating the mechanisms of illicit fund transfers between nodes to enhance the interpretability and transparency of the AML models. Experimental results suggest that our approach is scalable and effective at detecting money laundering from real and synthetic transaction graphs. © 2013 IEEE. | H20: Scopus | I20: =IF(B20="","",IF(AND(F20<>"",SUMPRODUCT(--ISNUMBER(SEARCH(Preseleccionados!$A$2:$A$11,F20)))>0),"YA ESTÁ",IF(AND(F20<>"",COUNTIF($F$3:F20,F20)>1),"REPETIDO",""))) | J20: =IF(OR(B20="",I20<>""),"",IF(MOD(COUNTIFS($B$3:B20,"<>",$I$3:I20,""),2)=1,"Carlos","Joaquín")) | P20: =IF(J20="","",IF(K20="Sale","Descartado",IF(L20="Sale","Descartado",IF(OR(M20="Q3",M20="Q4",M20="No aparece"),"Descartado",IF(N20="Sale","Descartado",IF(O20="Sigue","APROBADO","En proceso")))))) | Q20: Rwth Aachen University, Department of Information Systems and Databases, Aachen, 52074, Germany; Fraunhofer Fit, Department of Data Science and Artificial Intelligence, Sankt Augustin, 53757, Germany; École Normale Supérieure (ENS), Paris, 75005, France; Cosmian, Paris, 75008, France | R20: Bancos
A21: =IF(B21="","",ROW()-2) | B21: Incorporating machine learning and a risk-based strategy in an anti-money laundering multiagent system | C21: Alexandre C.R.; Balsa J. | D21: 2023 | E21: Expert Systems with Applications | F21: 10.1016/j.eswa.2023.119500 | G21: Over the last decade, the international community has become more aware of the danger and harm caused by the practice of the crime of Money Laundering (ML). Organizations to combat this crime were created and the existing laws were expanded and tightened. Complex legislation, combined with the increase in the volume of financial transactions involved in money laundering schemes, motivated research targeting the improvement and automation of the critical processes of detecting, signaling and communicating suspicious clients. The Anti-Money Laundering (AML) activity is strongly impacted and dependent on this process, which has evolved slowly, in part due to its subjectivity and complexity. This article presents the characteristics of a multiagent system that incorporates machine learning and risk components to identify and flag suspicious bank clients. It also seeks to help human specialists in the analysis of suspicious behavior by these clients. The knowledge bases are obtained through data mining over a real database, obtaining for each client a transactional behavior pattern, enriched with specific rules based on legal aspects, and on the expertise of the AML analysts of the financial institution that funds this research. The adopted risk strategy seeks to identify and classify the ML risk level of each flagged client. To evaluate its results, the system analyzed six months of actual transactions. A set of candidate clients was produced and subsequently investigated by the financial institution's AML analysts, who proved a high degree of correctness in the indicated suspicions, including cases that were not flagged by the antecedent systems in execution for decades at the institution. © 2023 | H21: Scopus | I21: =IF(B21="","",IF(AND(F21<>"",SUMPRODUCT(--ISNUMBER(SEARCH(Preseleccionados!$A$2:$A$11,F21)))>0),"YA ESTÁ",IF(AND(F21<>"",COUNTIF($F$3:F21,F21)>1),"REPETIDO",""))) | J21: =IF(OR(B21="",I21<>""),"",IF(MOD(COUNTIFS($B$3:B21,"<>",$I$3:I21,""),2)=1,"Carlos","Joaquín")) | K21: Sigue | L21: Sigue | P21: =IF(J21="","",IF(K21="Sale","Descartado",IF(L21="Sale","Descartado",IF(OR(M21="Q3",M21="Q4",M21="No aparece"),"Descartado",IF(N21="Sale","Descartado",IF(O21="Sigue","APROBADO","En proceso")))))) | Q21: LASIGE, Faculdade de Ciências da Universidade de Lisboa, Edifício C6, Campo Grande, Lisboa, 1749-016, Portugal | R21: Bancos
A22: =IF(B22="","",ROW()-2) | B22: Finding money launderers using heterogeneous graph neural networks | C22: Johannessen F.; Jullum M. | D22: 2025 | E22: Journal of Finance and Data Science | F22: 10.1016/j.jfds.2025.100175 | G22: The finance industry depends on effective anti-money laundering (AML) systems to ensure compliance and maintain operational efficiency. However, existing AML systems, which are predominantly rule-based, frequently struggle to detect money laundering accurately. In particular, their inability to learn from historical data and properly account for diverse customer behavior is problematic. Also accounting for the vast amounts of transactional data generated daily, this challenge calls for big data analytics and advanced machine learning techniques. In line with this, the present paper explores a graph neural network (GNN) approach, a state-of-the-art machine learning technique, to identify money laundering activities within a large heterogeneous network constructed from real-world bank transactions and business role data from DNB, Norway’s largest bank. To this end, we extend the (homogeneous) Message Passing Neural Network (MPNN) architecture to operate on a heterogeneous graph, and demonstrate its strong performance in detecting money laundering activities. We showcase the suitability of utilizing GNN methodology to improve electronic surveillance systems for detecting money laundering, thereby contributing a pioneering approach to AML through the application of advanced data science techniques. To the best of our knowledge, this is the first publication applying heterogeneous GNNs for AML purposes with a large real-world heterogeneous network. Copyright © 2025. Publishing services by Elsevier B.V. | H22: Scopus | I22: =IF(B22="","",IF(AND(F22<>"",SUMPRODUCT(--ISNUMBER(SEARCH(Preseleccionados!$A$2:$A$11,F22)))>0),"YA ESTÁ",IF(AND(F22<>"",COUNTIF($F$3:F22,F22)>1),"REPETIDO",""))) | J22: =IF(OR(B22="",I22<>""),"",IF(MOD(COUNTIFS($B$3:B22,"<>",$I$3:I22,""),2)=1,"Carlos","Joaquín")) | P22: =IF(J22="","",IF(K22="Sale","Descartado",IF(L22="Sale","Descartado",IF(OR(M22="Q3",M22="Q4",M22="No aparece"),"Descartado",IF(N22="Sale","Descartado",IF(O22="Sigue","APROBADO","En proceso")))))) | Q22: DNB, P.O. Box 1600, Sentrum, Oslo, NO-0021, Norway; Norwegian Computing Center, P.O. Box 114, Blindern, Oslo, NO-0314, Norway | R22: Bancos
A23: =IF(B23="","",ROW()-2) | B23: Unveiling sentiments of the cullen commission: Exploring AML compliance and regulation through deep learning techniques | C23: Lokanan M.E. | D23: 2025 | E23: Journal of Economic Criminology | F23: 10.1016/j.jeconc.2025.100138 | G23: This paper examines the role of anti-money laundering (AML) regulations and compliance in combating money laundering and terrorist financing (ML/TF) in Canada. AML regulations establish guidelines for financial institutions to identify, prevent, and report suspicious activities. However, tensions often arise between AML compliance and regulation due to the challenges associated with implementing and adhering to AML regulations. This paper aims to investigate the sentiments expressed by individuals involved in AML compliance and regulation regarding the effectiveness of AML measures in the Canadian financial sector. The paper uses advanced deep learning (DL) methods like convolutional neural networks (CNN), recurrent neural networks with long short-term memory (RNN+LSTM), and pre-trained models like GloVe and BERT to explore emotions in the context of AML compliance and regulation. The findings indicate that DL models excel at accurately classifying sentiments from testimonies related to AML compliance and regulation. However, there are challenges in accurately capturing negative sentiments, which reflect the complexities and nuances associated with expressing criticisms about regulatory standards. The study emphasizes the importance of understanding the interplay between rational decision-making in compliance and the inherent conflicts with regulation. This article also highlights how DL models can potentially enhance sentiment analysis in the AML enterprise, enabling analysts to make decisions and policies based on financial intelligence. Nevertheless, DL models are not always easy to comprehend. Further research is needed to enhance the understandability and scalability of DL models when analyzing different AML datasets. © 2025 | H23: Scopus | I23: =IF(B23="","",IF(AND(F23<>"",SUMPRODUCT(--ISNUMBER(SEARCH(Preseleccionados!$A$2:$A$11,F23)))>0),"YA ESTÁ",IF(AND(F23<>"",COUNTIF($F$3:F23,F23)>1),"REPETIDO",""))) | J23: =IF(OR(B23="",I23<>""),"",IF(MOD(COUNTIFS($B$3:B23,"<>",$I$3:I23,""),2)=1,"Carlos","Joaquín")) | K23: Sale | P23: =IF(J23="","",IF(K23="Sale","Descartado",IF(L23="Sale","Descartado",IF(OR(M23="Q3",M23="Q4",M23="No aparece"),"Descartado",IF(N23="Sale","Descartado",IF(O23="Sigue","APROBADO","En proceso")))))) | Q23: Faculty of Management. Royal Roads University, 2005 Sooke Road, royalroads.ca, Victoria, V9B 5Y2, BC, Canada | R23: Bancos
A24: =IF(B24="","",ROW()-2) | B24: Are the old ways of transaction monitoring dead? | C24: Gilson C. | D24: 2024 | E24: Journal of Financial Compliance | F24: 10.69554/RJCX4578 | G24: Financial institutions continue to face the challenge of demonstrating a comprehensive anti-money laundering (AML) transaction monitoring programme that is designed to detect, and aligns with, relevant Federal Financial Institutions Examinations Council (FFIEC) red flags without explicit, consistent confirmation on whether the escalations (ie Suspicious Activity Report [SAR] filings) are correct or valuable. Historically, this led most banks to adopt the use of typology-based if/then rules, resulting in a significant volume of alerts to be reviewed and dispositioned, with only a small portion being identified as potentially suspicious. While machine learning models are touted as an obvious fix to this problem, many banks may find such solutions to be far too expensive, complex and/or resource intensive. In order to answer the question, ‘are the old ways of transaction monitoring dead?’, this paper offers and evaluates various practical solutions, ranging from simple to sophisticated, to reduce false positive alerts generated by traditional AML transaction monitoring applications. © 2024, Henry Stewart Publications. All rights reserved. | H24: Scopus | I24: =IF(B24="","",IF(AND(F24<>"",SUMPRODUCT(--ISNUMBER(SEARCH(Preseleccionados!$A$2:$A$11,F24)))>0),"YA ESTÁ",IF(AND(F24<>"",COUNTIF($F$3:F24,F24)>1),"REPETIDO",""))) | J24: =IF(OR(B24="",I24<>""),"",IF(MOD(COUNTIFS($B$3:B24,"<>",$I$3:I24,""),2)=1,"Carlos","Joaquín")) | P24: =IF(J24="","",IF(K24="Sale","Descartado",IF(L24="Sale","Descartado",IF(OR(M24="Q3",M24="Q4",M24="No aparece"),"Descartado",IF(N24="Sale","Descartado",IF(O24="Sigue","APROBADO","En proceso")))))) | Q24: U.S. Bank, United States; U.S. Bank, 190 S. LaSalle Ave., Chicago, 60603, IL, United States | R24: Bancos
A25: =IF(B25="","",ROW()-2) | B25: Money Laundering Detection in Financial Institutions Using Machine Learning | C25: Masood N.S.; Sakr R.H.; Eleneen A.A. | D25: 2026 | E25: Journal of Computer Science | F25: 10.3844/jcssp.2026.1330.1343 | G25: This research aims to develop a system based on machine learning techniques for the accurate detection and classification of money laundering transactions. This system utilizes real and synthetic financial data, including the IBM AML dataset and synthetic financial databases. The methodology included data collection and cleaning, feature extraction from transaction behavior, and training several classification algorithms, including Random Forest, Support Vector Machine (SVM), and LogitBoost. A hybrid model was also built using a stacking approach to leverage the advantages of each algorithm. The models were evaluated using various statistical measures, including precision, recall, and the F1 score, as well as performance analysis via ROC and PR curves. The results demonstrated that the hybrid model outperformed individual models in detecting suspicious transactions and reducing errors, enhancing its effectiveness as an intelligent tool to support financial institutions and regulatory authorities in the early detection of financial crimes. The research recommends expanding the scope of data used and leveraging deep learning techniques to enhance the system's efficiency and accuracy. © 2026 Noor Samer Masood, Rasha Hassan Sakr and Amal Abou Eleneen. This open-access article is distributed under a Creative Commons Attribution (CC-BY) 4.0 license. | H25: Scopus | I25: =IF(B25="","",IF(AND(F25<>"",SUMPRODUCT(--ISNUMBER(SEARCH(Preseleccionados!$A$2:$A$11,F25)))>0),"YA ESTÁ",IF(AND(F25<>"",COUNTIF($F$3:F25,F25)>1),"REPETIDO",""))) | J25: =IF(OR(B25="",I25<>""),"",IF(MOD(COUNTIFS($B$3:B25,"<>",$I$3:I25,""),2)=1,"Carlos","Joaquín")) | K25: Sigue | L25: Sigue | P25: =IF(J25="","",IF(K25="Sale","Descartado",IF(L25="Sale","Descartado",IF(OR(M25="Q3",M25="Q4",M25="No aparece"),"Descartado",IF(N25="Sale","Descartado",IF(O25="Sigue","APROBADO","En proceso")))))) | Q25: Department of Computer Science, Faculty of Computers and Information, Mansoura University, Mansoura, Egypt | R25: Bancos
A26: =IF(B26="","",ROW()-2) | B26: Explainable artificial intelligence models for detecting suspicious bank transactions | C26: Narasapuram N.K.; Shah S.A.A.; Shiratuddin M.F.; Sohel F. | D26: 2026 | E26: International Journal of Machine Learning and Cybernetics | F26: 10.1007/s13042-026-02994-w | G26: Detecting financial crime is a complex challenge due to evolving criminal strategies and fragmented detection systems, particularly in the areas of money laundering and fraud. While it is easy to implement, traditional rule-based approaches lack adaptability to new threats, and machine learning models, though more effective, often function as opaque "black boxes," limiting their practical use in regulated domains like banking, where interpretability and accountability are essential. This research presents a novel framework that combines intrinsic and post-hoc XAI techniques to detect suspicious bank transactions. Intrinsic methods provide model-inherent transparency, while post-hoc methods offer behavior-level explanations, enabling robust cross-verification of the model’s decision logic. This dual-layered explainability supports both global understanding of the model and local interpretability for individual predictions. Experimental evaluation on synthetic datasets shows that the proposed framework achieves promising results, with F1 scores ranging from 0.54 to 0.63 for anti-money laundering (AML) detection and 0.66 to 0.78 for fraud detection, depending on the underlying model architecture. The use of explainability tools also enables the identification of key features shared across fraud and AML cases, revealing structural similarities. These insights demonstrate that a unified model can effectively capture both crime types, offering practical benefits for integrated financial crime risk management. By addressing the information silos caused by different regulatory frameworks and departmental responsibilities, this work supports the development of joint investigative systems and facilitates better communication between compliance teams. In addition, the explainable nature of the models helps satisfy regulatory scrutiny while improving investigator trust and decision support. The proposed approach contributes to the growing field of interpretable machine learning by providing a scalable, auditable, and regulator-friendly solution for detecting complex financial crimes. © The Author(s) 2026. | H26: Scopus | I26: =IF(B26="","",IF(AND(F26<>"",SUMPRODUCT(--ISNUMBER(SEARCH(Preseleccionados!$A$2:$A$11,F26)))>0),"YA ESTÁ",IF(AND(F26<>"",COUNTIF($F$3:F26,F26)>1),"REPETIDO",""))) | J26: =IF(OR(B26="",I26<>""),"",IF(MOD(COUNTIFS($B$3:B26,"<>",$I$3:I26,""),2)=1,"Carlos","Joaquín")) | P26: =IF(J26="","",IF(K26="Sale","Descartado",IF(L26="Sale","Descartado",IF(OR(M26="Q3",M26="Q4",M26="No aparece"),"Descartado",IF(N26="Sale","Descartado",IF(O26="Sigue","APROBADO","En proceso")))))) | Q26: School of Information Technology, Murdoch University, 90 South Street, Murdoch, 6150, WA, Australia; School of Science, Edith Cowan University, Perth, WA, Australia | R26: Bancos
A27: =IF(B27="","",ROW()-2) | B27: Predicting Money Laundering Using Machine Learning and Artificial Neural Networks Algorithms in Banks | C27: Lokanan M.E. | D27: 2024 | E27: Journal of Applied Security Research | F27: 10.1080/19361610.2022.2114744 | G27: This paper aims to build a machine learning and a neural network model to detect the probability of money laundering in banks. The paper's data came from a simulation of actual transactions flagged for money laundering in Middle Eastern banks. The main findings highlight that criminal networks mainly use the integration stage to integrate money into the financial system. Fraudsters prefer to launder funds in the early hours, morning followed by the business day's afternoon time intervals. Additionally, the Naïve Bayes and Random Forest classifiers were identified as the two best-performing models to predict bank money laundering transactions. © 2022 Taylor & Francis Group, LLC. | H27: Scopus | I27: =IF(B27="","",IF(AND(F27<>"",SUMPRODUCT(--ISNUMBER(SEARCH(Preseleccionados!$A$2:$A$11,F27)))>0),"YA ESTÁ",IF(AND(F27<>"",COUNTIF($F$3:F27,F27)>1),"REPETIDO",""))) | J27: =IF(OR(B27="",I27<>""),"",IF(MOD(COUNTIFS($B$3:B27,"<>",$I$3:I27,""),2)=1,"Carlos","Joaquín")) | K27: Sigue | L27: Sigue | P27: =IF(J27="","",IF(K27="Sale","Descartado",IF(L27="Sale","Descartado",IF(OR(M27="Q3",M27="Q4",M27="No aparece"),"Descartado",IF(N27="Sale","Descartado",IF(O27="Sigue","APROBADO","En proceso")))))) | Q27: Faculty of Management, Royal Roads University, Victoria, Canada | R27: Bancos
A28: =IF(B28="","",ROW()-2) | B28: A Hybrid Machine Learning Model for Streaming Frequency-Based Anomaly Detection in Banking Transactions | C28: Hersyaputra M.S.; Jaya M.T.T.; Anggraini R.N.E. | D28: 2026 | E28: Journal of Information and Communication Technology | F28: 10.32890/jict2026.25.1.4 | G28: The increasing sophistication of fraudulent activities in digital financial systems necessitates real-time anomaly detection models that can adapt to evolving transactional behaviours. While prior research has explored machine learning approaches for fraud detection, most rely on static datasets and overlook temporal dependencies inherent in financial transaction streams. This study addresses this critical gap by proposing a hybrid anomaly detection model that integrates dynamic streaming-frequency analysis via a 7-day sliding window, an unsupervised Long Short-Term Memory (LSTM) -autoencoder for anomaly scoring, and a supervised Artificial Neural Network (ANN) for classification. The sliding window mechanism enables the model to capture short-term temporal fluctuations and behavioural patterns, aligning with the streaming nature of financial data. The LSTM-autoencoder is trained exclusively on normal transaction sequences to learn temporal dependencies and compute reconstruction errors, which serve as deep anomaly features. These features are then fed into the ANN to classify transactions as normal or anomalous. Experimental results on the IBM Anti-Money Laundering (AML) dataset demonstrate the effectiveness of the proposed framework, achieving a classification accuracy of 99.92%, precision of 94.12%, recall of 88.43%, and F1 score of 91.19%. This layered architecture not only enhances early detection of anomalous behaviour but also provides a scalable, adaptive solution for real-time fraud detection in streaming financial environments. © 2026, Universiti Utara Malaysia Press. All rights reserved. | H28: Scopus | I28: =IF(B28="","",IF(AND(F28<>"",SUMPRODUCT(--ISNUMBER(SEARCH(Preseleccionados!$A$2:$A$11,F28)))>0),"YA ESTÁ",IF(AND(F28<>"",COUNTIF($F$3:F28,F28)>1),"REPETIDO",""))) | J28: =IF(OR(B28="",I28<>""),"",IF(MOD(COUNTIFS($B$3:B28,"<>",$I$3:I28,""),2)=1,"Carlos","Joaquín")) | P28: =IF(J28="","",IF(K28="Sale","Descartado",IF(L28="Sale","Descartado",IF(OR(M28="Q3",M28="Q4",M28="No aparece"),"Descartado",IF(N28="Sale","Descartado",IF(O28="Sigue","APROBADO","En proceso")))))) | Q28: Department of Informatics, Institut Teknologi Sepuluh Nopember, Indonesia | R28: Bancos
A29: =IF(B29="","",ROW()-2) | B29: Comparative analysis of machine learning models for the detection of fraudulent banking transactions | C29: Preciado Martínez P.M.; Reier Forradellas R.F.; Garay Gallastegui L.M.; Náñez Alonso S.L. | D29: 2025 | E29: Cogent Business and Management | F29: 10.1080/23311975.2025.2474209 | G29: This research presents a comparative analysis of machine learning models for detecting fraudulent banking transactions, a growing problem in the digital financial sector. The aim is to evaluate and determine the most effective model for identifying suspicious transactions, overcoming the challenge of a highly imbalanced dataset. Using data from 565,000 real-world transfers, models based on algorithms such as Random Forest, Neural Networks and Naive Bayes were built and tested. Of these, the Random Forest model proved to be the most robust, achieving 100% accuracy for legitimate transactions and 95.79% accuracy for fraud detection. This level of accuracy reinforces its viability for implementation in real-time banking systems. This result underlines the feasibility of integrating such a model into banking systems for real-time analysis, allowing the interception of dubious transactions. This capability would drastically reduce exposure to financial fraud, optimizing transaction security without compromising operational fluidity. In addition, limitations were identified and future approaches discussed, including oversampling techniques and adjusting class weights to improve detection in unbalanced datasets. © 2025 The Author(s). Published by Informa UK Limited, trading as Taylor & Francis Group. | H29: Scopus | I29: =IF(B29="","",IF(AND(F29<>"",SUMPRODUCT(--ISNUMBER(SEARCH(Preseleccionados!$A$2:$A$11,F29)))>0),"YA ESTÁ",IF(AND(F29<>"",COUNTIF($F$3:F29,F29)>1),"REPETIDO",""))) | J29: =IF(OR(B29="",I29<>""),"",IF(MOD(COUNTIFS($B$3:B29,"<>",$I$3:I29,""),2)=1,"Carlos","Joaquín")) | K29: Sigue | L29: Sigue | P29: =IF(J29="","",IF(K29="Sale","Descartado",IF(L29="Sale","Descartado",IF(OR(M29="Q3",M29="Q4",M29="No aparece"),"Descartado",IF(N29="Sale","Descartado",IF(O29="Sigue","APROBADO","En proceso")))))) | Q29: Technology and Innovation Unit, Caja Rural de Almendralejo SCC, Badajoz, Spain; DEKIS Research Group, Department of Economics, Faculty of Social and Legal Sciences, Catholic University of Ávila, Avila, Spain; UNIR - International University of La Rioja, Logroño, Spain | R29: Bancos
A30: =IF(B30="","",ROW()-2) | B30: Transaction Monitoring Netherlands: Fighting financial crime through data collaboration and advanced analytics | C30: Siegers N. | D30: 2024 | E30: Journal of Payments Strategy and Systems | F30: 10.69554/jjpz9847 | G30: This paper discusses the experience of Transactie Monitoring Nederland (TMNL) — a collaboration between ABN AMRO, ING, Rabobank, Triodos Bank and De Volksbank, established in July 2020 to enhance financial security and compliance within the Dutch financial sector. The paper explores TMNL’s impact, the key lessons learned from its implementation and operation, best practices and its potential future role in safeguarding the integrity of the financial sector. As the paper explains, there is a growing consensus that more can be done to strengthen the framework for fighting financial crime through public–private partnerships and increased data/ information sharing. To this end, TMNL works to identify potentially unusual transaction patterns that are not visible to individual banks in isolation, underscoring the significance of collaboration and information sharing among financial institutions (and with other key players in the prevention ecosystem), and developing a united front against financial crime. The paper calls for the integration of artificial intelligence and machine learning in identifying complex patterns and anomalies in transaction data and emphasises the need for this to happen in a secure, sustained and viable fashion. It also underscores the ongoing need for regulatory adaptability, arguing that as financial crimes evolve, regulatory frameworks must be dynamic to address emerging challenges effectively. In conclusion, the paper provides valuable insights into the successful implementation of collaborative compliance efforts and the continuous adaptations required to combat financial crime. © Henry Stewart Publications. | H30: Scopus | I30: =IF(B30="","",IF(AND(F30<>"",SUMPRODUCT(--ISNUMBER(SEARCH(Preseleccionados!$A$2:$A$11,F30)))>0),"YA ESTÁ",IF(AND(F30<>"",COUNTIF($F$3:F30,F30)>1),"REPETIDO",""))) | J30: =IF(OR(B30="",I30<>""),"",IF(MOD(COUNTIFS($B$3:B30,"<>",$I$3:I30,""),2)=1,"Carlos","Joaquín")) | P30: =IF(J30="","",IF(K30="Sale","Descartado",IF(L30="Sale","Descartado",IF(OR(M30="Q3",M30="Q4",M30="No aparece"),"Descartado",IF(N30="Sale","Descartado",IF(O30="Sigue","APROBADO","En proceso")))))) | Q30: Transactie Monitoring Nederland B.V, Netherlands | R30: Bancos
A31: =IF(B31="","",ROW()-2) | B31: Automating the Detection of Fraudulent Activities in Online Banking Service | C31: Asomura I.; Iijima R.; Mori T. | D31: 2023 | E31: Journal of Information Processing | F31: 10.2197/IPSJJIP.31.643 | G31: Banks offering Online Banking services need to detect and prevent unauthorized electronic funds transfers to reduce financial crime risk. They monitor online banking transaction histories and use their own methods to detect and prevent unauthorized electronic fund transfers. However, unauthorized electronic fund transfers by criminals have not been eliminated. The average rate of false positives in the transaction monitoring systems installed in Japanese banks is up to 99%, indicating that the monitoring systems are not fully functional. Furthermore, the personnel responsible for fraud detection must manually check a large number of false positives, making it difficult for operators to be productive in their assigned tasks. Based on the above background, we develop a method to detect unauthorized electronic fund transfers and suspicious transactions with high accuracy using machine learning algorithms and evaluate its accuracy. Specifically, a supervised machine learning algorithm is applied to detect fraudulent transactions automatically. We evaluated the proposed method on a large set of online banking transaction data provided by a major Japanese bank for the period March 2019 to May 2020. We demonstrated that our approach could detect fraudulent activity with extremely high accuracy; FPR=0.000 and FNR=0.005 can be achieved for a security policy that minimizes false positives. © 2023 Information Processing Society of Japan. | H31: Scopus | I31: =IF(B31="","",IF(AND(F31<>"",SUMPRODUCT(--ISNUMBER(SEARCH(Preseleccionados!$A$2:$A$11,F31)))>0),"YA ESTÁ",IF(AND(F31<>"",COUNTIF($F$3:F31,F31)>1),"REPETIDO",""))) | J31: =IF(OR(B31="",I31<>""),"",IF(MOD(COUNTIFS($B$3:B31,"<>",$I$3:I31,""),2)=1,"Carlos","Joaquín")) | K31: Sigue | L31: Sigue | P31: =IF(J31="","",IF(K31="Sale","Descartado",IF(L31="Sale","Descartado",IF(OR(M31="Q3",M31="Q4",M31="No aparece"),"Descartado",IF(N31="Sale","Descartado",IF(O31="Sigue","APROBADO","En proceso")))))) | Q31: Waseda University, Shinjuku, Tokyo, 169–8555, Japan; NICT, Tokyo, Koganei, 184–8795, Japan; RIKEN AIP, Chuo, Tokyo, 103–0027, Japan | R31: Bancos
A32: =IF(B32="","",ROW()-2) | B32: Improving client risk classification with machine learning to increase anti-money laundering detection efficiency | C32: Reite E.J.; Karlsen J.; Westgaard E.G. | D32: 2025 | E32: Journal of Money Laundering Control | F32: 10.1108/JMLC-03-2024-0040 | G32: Purpose: This study aims to describe and empirically explore a new method for bank anti-money laundering (AML) systems using machine learning models. Current automated money laundering detection systems are notorious for flagging many false positives, causing bank employees to spend unnecessary time manually checking transactions that do not constitute money laundering. Decreasing the number of false positives can free up resources for investigating money laundering. Design/methodology/approach: This study uses unique bank data on small- and medium-sized enterprises (SMEs) to examine how various client risk classification models can predict future suspicious transactions. This study explores various sources of client risk data and machine-learning approaches. Findings: Client risk classification models can accurately predict suspicious future transactions. Adding accounting data and credit score information to client risk classification dramatically improves accuracy. This makes it easier to balance the risk of missing suspicious transactions with the need to reduce the number of false positives. Practical implications: The suggested approach with readily available data sources and a focus on classifying client risk in a dynamic model can help banks significantly improve their efficiency by targeting their AML efforts toward the riskiest clients. Originality/value: To the best of the authors’ knowledge, this study is the first to empirically explore machine learning in client risk classification, document how machine learning in client risk classification can significantly reduce false positives by incorporating novel, but readily available sources, such as credit risk and accounting data. © 2024, Emerald Publishing Limited. | H32: Scopus | I32: =IF(B32="","",IF(AND(F32<>"",SUMPRODUCT(--ISNUMBER(SEARCH(Preseleccionados!$A$2:$A$11,F32)))>0),"YA ESTÁ",IF(AND(F32<>"",COUNTIF($F$3:F32,F32)>1),"REPETIDO",""))) | J32: =IF(OR(B32="",I32<>""),"",IF(MOD(COUNTIFS($B$3:B32,"<>",$I$3:I32,""),2)=1,"Carlos","Joaquín")) | P32: =IF(J32="","",IF(K32="Sale","Descartado",IF(L32="Sale","Descartado",IF(OR(M32="Q3",M32="Q4",M32="No aparece"),"Descartado",IF(N32="Sale","Descartado",IF(O32="Sigue","APROBADO","En proceso")))))) | Q32: NTNU Business School, Norwegian University of Science and Technology, Trondheim, Norway; Department of Economics, Norwegian University of Science and Technology, Trondheim, Norway | R32: Bancos
A33: =IF(B33="","",ROW()-2) | B33: DESIGN AND IMPLEMENTATION OF DISK-BASED GRAPH FEATURE PREPROCESSOR FOR TERRORIST FINANCING DETECTION | C33: Bolshibayeva A.; Rakhmetulayeva S.; Kulbayeva A.; Yasar A.-U.-H. | D33: 2025 | E33: Eastern-European Journal of Enterprise Technologies | F33: 10.15587/1729-4061.2025.340033 | G33: The object of the study is streaming payment transactions modeled as directed multigraphs. This study investigates terrorism-financing detection in payment transaction networks using disk-based graph processing and anomaly detection. The key problem addressed is the high memory consumption of graph-based detectors, which prevents analysis on systems with limited Random Access Memory, typical of small and mid-sized financial institutions. A disk-based graph feature preprocessor (DGFP) was made to get around this problem. During stream processing, DGFP dynamically labels connected components and identifies eight graph patterns characteristic of terrorist financing, including fan-in/fan-out stars and multi-hop chains. The system persists component descriptors to a columnar store on an SSD and uses an LRU-managed hot cache to serve the features, enabling real-time transaction scoring with sub-second latency. On a two-million-transaction AMLSim stream, the system integrates with a lightweight Isolation Forest and achieves an F1-score of 0.76 while reducing peak RAM from 18.3 GB to 9.8 GB and maintaining 410 ± 15 ms mean latency for 10 000 transactions. Per-motif computation remains ≤ 28.4 ms (median < 24 ms), supporting real-time scoring on commodity hardware. DGFP produces model-agnostic graph features that interoperate with standard anomaly detectors without retraining GNNs. Contributions of this research include an external memory architecture for streaming graph feature extraction; a motif-aware feature labeling scheme stored on SSD and cached by LRU; and an empirical evaluation demonstrating real-time performance and memory efficiency improvements on anti-money laundering data. Copyright © 2025, Authors. | H33: Scopus | I33: =IF(B33="","",IF(AND(F33<>"",SUMPRODUCT(--ISNUMBER(SEARCH(Preseleccionados!$A$2:$A$11,F33)))>0),"YA ESTÁ",IF(AND(F33<>"",COUNTIF($F$3:F33,F33)>1),"REPETIDO",""))) | J33: =IF(OR(B33="",I33<>""),"",IF(MOD(COUNTIFS($B$3:B33,"<>",$I$3:I33,""),2)=1,"Carlos","Joaquín")) | P33: =IF(J33="","",IF(K33="Sale","Descartado",IF(L33="Sale","Descartado",IF(OR(M33="Q3",M33="Q4",M33="No aparece"),"Descartado",IF(N33="Sale","Descartado",IF(O33="Sigue","APROBADO","En proceso")))))) | Q33: Department of Information Systems, International IT University, Manas str., 34/1, Almaty, 050060, Kazakhstan; Department of Cybersecurity, Information Processing and Storage, Satbayev University, Satbaev str., 22, Almaty, 050013, Kazakhstan; Department of Information Systems, International IT University, Manas str., 34/1, Almaty, 050060, Kazakhstan; Transportation Research Institute (IMOB), Hasselt University, Martelarenlaan str., 42, Diepenbeek, 3590, Belgium | R33: Bancos
A34: =IF(B34="","",ROW()-2) | B34: Enhancing AML compliance: a machine learning approach to suspicious activity detection through routine activity theory | C34: Lokanan M.E. | D34: 2025 | E34: Journal of Money Laundering Control | F34: 10.1108/JMLC-07-2024-0114 | G34: Purpose This study explores the application of machine learning (ML) algorithms to enhance the detection and reporting of Suspicious Activity Reports (SARs) in California’s financial sector. This research aims to improve anti-money laundering (AML) compliance by evaluating the effectiveness of advanced ML techniques, specifically CatBoost and Decision Tree algorithms, in identifying suspicious financial transactions. Design/methodology/approach This research uses a comprehensive methodological framework involving the analysis of 45,000 SAR filings from financial institutions and regulatory agencies in California, dating back to 2018. Various ML algorithms, including linear regression, random forest, decision tree and CatBoost, are used to analyze SAR filing patterns and predict suspicious transactions. Findings The findings reveal that CatBoost outperforms other models, offering a better fit to the data and higher predictive accuracy with a low RMSE and high cross-validation scores. The Decision Tree algorithm also demonstrates significant promise but is slightly less effective than CatBoost. This study confirms that ML algorithms, particularly CatBoost, significantly improve the detection and reporting of suspicious financial activities, thereby enhancing AML compliance. Originality/value This research contributes to the literature by integrating advanced ML techniques into AML compliance, moving beyond traditional statistical approaches. The findings provide practical implications for financial institutions, highlighting the potential of ML algorithms to enhance the effectiveness of SAR filings and bolster regulatory efforts in mitigating financial crime. This study underscores the value of ML in developing targeted policies to curb illicit financial activities and advance AML analytical capabilities. © 2025 Emerald Publishing Limited | H34: Scopus | I34: =IF(B34="","",IF(AND(F34<>"",SUMPRODUCT(--ISNUMBER(SEARCH(Preseleccionados!$A$2:$A$11,F34)))>0),"YA ESTÁ",IF(AND(F34<>"",COUNTIF($F$3:F34,F34)>1),"REPETIDO",""))) | J34: =IF(OR(B34="",I34<>""),"",IF(MOD(COUNTIFS($B$3:B34,"<>",$I$3:I34,""),2)=1,"Carlos","Joaquín")) | P34: =IF(J34="","",IF(K34="Sale","Descartado",IF(L34="Sale","Descartado",IF(OR(M34="Q3",M34="Q4",M34="No aparece"),"Descartado",IF(N34="Sale","Descartado",IF(O34="Sigue","APROBADO","En proceso")))))) | Q34: Faculty of Management, Royal Roads University, Victoria, Canada | R34: Bancos
A35: =IF(B35="","",ROW()-2) | B35: Legal implications of automated suspicious transaction monitoring: enhancing integrity of AI | C35: Turksen U.; Benson V.; Adamyk B. | D35: 2024 | E35: Journal of Banking Regulation | F35: 10.1057/s41261-024-00233-2 | G35: The fast-paced advances of technology, including artificial intelligence (AI) and machine learning (ML), continue to create new opportunities for banks and other financial institutions. This study reveals the barriers to trust in AI by prudential banking supervisors (compliance with regulations). We conducted a qualitative study on the drivers for adoption of explainability technologies that increase transparency and understanding of complex algorithms (some of the underpinning legal principles in the proposed EU AI Act). By using human-centred and ethics-by-design methods coupled with interviews of the key stakeholders from Eastern European private and public banks and IT AI/ML developers, this research has identified the key challenges concerning the employment of AI algorithms. The results indicate a conflicting view of AI barriers whilst revealing the importance of AI/ML systems in banks, the growing willingness of banks to use such systems more widely, and the problematic aspects of implementing AI/ML systems related to their cost and economic efficiency. Keeping up with the complex regulation requirements comes at a significant cost to banks and financial firms. The focus of the empirical study, stakeholders in Ukraine, Estonia and Poland, was chosen because of the fact that there has been a sharp increase in the adoption of AI/ML models in this jurisdiction in the context of its war with Russia and the ensuing sanctions regime. While the “leapfrogging” AI/ML paths in each bank surveyed had its own drivers and challenges, these insights provide lessons for banks in other European jurisdictions. The analysis of four criminal cases brought against top banks and conclusions of the study indicate that the increase in predicate crimes for money laundering, constantly evolving sanctions regime along with the enhanced scrutiny and enforcement action against banks are hindering technology innovation and legal implications of using AI driven tools for compliance. © The Author(s) 2024. | H35: Scopus | I35: =IF(B35="","",IF(AND(F35<>"",SUMPRODUCT(--ISNUMBER(SEARCH(Preseleccionados!$A$2:$A$11,F35)))>0),"YA ESTÁ",IF(AND(F35<>"",COUNTIF($F$3:F35,F35)>1),"REPETIDO",""))) | J35: =IF(OR(B35="",I35<>""),"",IF(MOD(COUNTIFS($B$3:B35,"<>",$I$3:I35,""),2)=1,"Carlos","Joaquín")) | K35: Sale | P35: =IF(J35="","",IF(K35="Sale","Descartado",IF(L35="Sale","Descartado",IF(OR(M35="Q3",M35="Q4",M35="No aparece"),"Descartado",IF(N35="Sale","Descartado",IF(O35="Sigue","APROBADO","En proceso")))))) | Q35: Centre for Financial and Corporate Integrity, Coventry University, Coventry, CV1 2TU, United Kingdom; Aston Business School, Aston University, Birmingham, B4 7ET, United Kingdom | R35: Bancos
A36: =IF(B36="","",ROW()-2) | B36: Explainable and fair anti-money laundering models using a reproducible SHAP framework for financial institutions | C36: Mazumder P.T. | D36: 2026 | E36: Discover Artificial Intelligence | F36: 10.1007/s44163-026-00944-7 | G36: Financial institutions are under growing regulatory pressure to detect and report money laundering in a way that is accurate, auditable, and fair. This study introduces a reproducible machine learning pipeline for Anti-Money Laundering (AML) detection that integrates statistically validated synthetic data generation, class-imbalance handling, and post-hoc explainability. Using a 10,000-record synthetic AML dataset generated with the Synthetic Data Vaultand Faker, we train Random Forest and Multilayer Perceptron classifiers with class weighting and F2-optimized threshold tuning. Our primary objective is to maximize recall of suspicious transactions while maintaining operationally manageable alert volumes, reflecting regulatory expectations that missed suspicious activity should be minimized. Model performance is evaluated using PR-AUC, precision/recall for the suspicious class, F1 score, MCC, balanced accuracy, and probability calibration. Global and local model interpretability are achieved using TreeSHAP and KernelSHAP, enabling analysts to understand feature contributions and diagnose false positives and false negatives. Fairness audits across age and regional proxies reveal Equal Opportunity gaps, which are mitigated via post-processing threshold adjustments. Results show substantially improved AML recall at regulatory-compliant operating points, with improved precision relative to simple baselines, and provide transparent, auditable outputs aligned with the Bank Secrecy Act and FATF guidance. This work offers U.S. financial institutions a deployable framework that enhances compliance efficiency, supports supervisory review, and enables replication and industry benchmarking. © The Author(s) 2026. | H36: Scopus | I36: =IF(B36="","",IF(AND(F36<>"",SUMPRODUCT(--ISNUMBER(SEARCH(Preseleccionados!$A$2:$A$11,F36)))>0),"YA ESTÁ",IF(AND(F36<>"",COUNTIF($F$3:F36,F36)>1),"REPETIDO",""))) | J36: =IF(OR(B36="",I36<>""),"",IF(MOD(COUNTIFS($B$3:B36,"<>",$I$3:I36,""),2)=1,"Carlos","Joaquín")) | P36: =IF(J36="","",IF(K36="Sale","Descartado",IF(L36="Sale","Descartado",IF(OR(M36="Q3",M36="Q4",M36="No aparece"),"Descartado",IF(N36="Sale","Descartado",IF(O36="Sigue","APROBADO","En proceso")))))) | Q36: Department of Finance, Georgia State University, Atlanta, GA, United States | R36: Bancos
A37: =IF(B37="","",ROW()-2) | B37: Hybrid big data stream processing model for effective fraud detection in cash electronic payment cards | C37: Shamsinejad E.; Banirostam H.; BaniRostam T. | D37: 2026 | E37: International Journal of System Assurance Engineering and Management | F37: 10.1007/s13198-026-03367-w | G37: Fraud detection in banking systems is of critical importance due to its vital role in identifying unauthorized transactions and preventing financial losses. The complexity of data structures, high transaction volume, and continuous evolution of fraud patterns pose significant challenges. This paper presents an innovative system-level hybrid framework for fraud detection in electronic payment cards, which integrates unsupervised and supervised algorithms within a novel two-stage streaming pipeline featuring adaptive per-cardholder profiling, Dempster–Shafer-based score fusion, and drift-aware dynamic thresholds. While building upon established algorithms, the primary novelty lies in the architectural design and synergistic integration rather than new base methods. The model first constructs distinct user behavior profiles (based on transaction timing, amounts, and other features) with adaptive thresholds, periodically updated in the batch learning layer to handle concept drift in streaming environments. It then applies a two-stage filtering process: the fast preliminary filter uses unsupervised algorithms K-means clustering and Hidden Markov model (HMM) to rapidly detect anomalies and reduce candidates, selected for their efficiency, scalability, and complementary capture of spatial and temporal deviations. The explicit filter employs supervised algorithms K-nearest neighbors (KNN), Logistic Regression, and Decision Tree to classify remaining suspicious transactions with high precision, chosen for their effectiveness in imbalanced data, interpretability, local pattern recognition, and non-linear modeling. The framework also leverages the maximum difference between consecutive observations (defined as the largest absolute change in normalized scores or features between successive steps, motivated by its sensitivity to abrupt anomalies) as a key discriminative feature. The model is evaluated using classification metrics (cross-validation accuracy, recall, precision, F1-score) for categorical fraud detection and regression metrics (RMSE, MBE) for numerical anomaly prediction. Results on a large credit card transaction dataset show the proposed framework outperforms several state-of-the-art baselines (Random forest, XGBoost, Isolation forest, Autoencoder) with statistically significant improvements (p < 0.05 or better) in F1-score and recall, while achieving superior detection performance and computational efficiency. By combining multi-algorithm strengths with in-memory stream processing, this research delivers an effective, scalable solution for real-time fraud detection in electronic payment systems with built-in adaptability to evolving patterns. © The Author(s) under exclusive licence to The Society for Reliability Engineering, Quality and Operations Management (SREQOM), India and The Division of Operation and Maintenance, Lulea University of Technology, Sweden 2026. | H37: Scopus | I37: =IF(B37="","",IF(AND(F37<>"",SUMPRODUCT(--ISNUMBER(SEARCH(Preseleccionados!$A$2:$A$11,F37)))>0),"YA ESTÁ",IF(AND(F37<>"",COUNTIF($F$3:F37,F37)>1),"REPETIDO",""))) | J37: =IF(OR(B37="",I37<>""),"",IF(MOD(COUNTIFS($B$3:B37,"<>",$I$3:I37,""),2)=1,"Carlos","Joaquín")) | K37: Sigue | L37: Sigue | P37: =IF(J37="","",IF(K37="Sale","Descartado",IF(L37="Sale","Descartado",IF(OR(M37="Q3",M37="Q4",M37="No aparece"),"Descartado",IF(N37="Sale","Descartado",IF(O37="Sigue","APROBADO","En proceso")))))) | Q37: Computer Engineering (Software), Specializing in Data Science, Tehran, Iran; Master of Data Analytics, University of Niagara Falls, Niagara Falls, ON, Canada | R37: Bancos
A38: =IF(B38="","",ROW()-2) | B38: Qualifying and raising anti-money laundering alarms with deep learning | C38: Jensen R.I.T.; Iosifidis A. | D38: 2023 | E38: Expert Systems with Applications | F38: 10.1016/j.eswa.2022.119037 | G38: We propose a deep learning approach to qualify and raise anti-money laundering alarms in banks. The motivating idea is to replace predefined rules with latent features automatically extracted from transaction sequences. To this end, we experiment with recurrent and Transformer encoder layers. We test the approach with a large data set from Spar Nord Bank. Our best model employs gated recurrent units and self-attention. When used to qualify alarms raised by a traditional AML system, the model is able to reduce the number of false positives by more than 33.3% while retaining 98.8% of all true positives. In a small experiment, we also use the model to raise 75 new alarms on clients with high risk scores but with no traditional alarm inquiries in the last 12 months. After expert review, this prompted 26 clients to be reported to Danish authorities. © 2022 Elsevier Ltd | H38: Scopus | I38: =IF(B38="","",IF(AND(F38<>"",SUMPRODUCT(--ISNUMBER(SEARCH(Preseleccionados!$A$2:$A$11,F38)))>0),"YA ESTÁ",IF(AND(F38<>"",COUNTIF($F$3:F38,F38)>1),"REPETIDO",""))) | J38: =IF(OR(B38="",I38<>""),"",IF(MOD(COUNTIFS($B$3:B38,"<>",$I$3:I38,""),2)=1,"Carlos","Joaquín")) | P38: =IF(J38="","",IF(K38="Sale","Descartado",IF(L38="Sale","Descartado",IF(OR(M38="Q3",M38="Q4",M38="No aparece"),"Descartado",IF(N38="Sale","Descartado",IF(O38="Sigue","APROBADO","En proceso")))))) | Q38: Department of Electrical and Computer Engineering, Aarhus University, Finlandsgade 22, Aarhus, 8200, Denmark; Spar Nord Bank, Skelagervej 9, Aalborg, 9000, Denmark | R38: Bancos
A39: =IF(B39="","",ROW()-2) | B39: Fund transfer fraud detection: Analyzing irregular transactions and customer relationships with self-attention and graph neural networks | C39: Shih Y.-C.; Dai T.-S.; Chen Y.-P.; Ti Y.-W.; Wang W.-H.; Kuo Y. | D39: 2025 | E39: Expert Systems with Applications | F39: 10.1016/j.eswa.2024.125211 | G39: This paper presents a method for identifying fraudulent fund transfers using real bank data, analyzing customer information, transactional activities, and customer relationships. The preprocessing step transforms high-dimensional, irregular transaction time series into regular time series, then further compresses them in a latent space using a self-attention-based autoencoder. To address the scarcity of fraudulent data samples and mitigate training issues caused by data imbalance, various deep generative models, including the conditional variational autoencoder and Wasserstein generative adversarial network, are applied to generate additional fraudulent raw data and augment fraud samples in latent space. The reparameterization trick is integrated into the encoder–decoder structure to boost the model's generative capabilities. Additionally, a Graph Neural Network (GNN) is used to model customer relationships. The proposed approach utilizes end-to-end learning, integrating the autoencoder's reconstruction loss, KL divergence loss (when reparameterization trick is applied), and classification loss for fraud detection. To optimize computational resources, neighborhood sampling for GNN is combined with mini-batch training for the autoencoder, improving both training efficiency and model reliability. Comprehensive experiments demonstrate the effectiveness of the proposed fusion network, highlighting the importance of each component and preprocessing step. For example, the areas under the precision–recall curves for fraud detection show notable improvements in our model. For suspicious transactions identified by the bank's rules, other models range from 0.66% to 22.15%, while our model reached 27%. For non-suspicious transactions, other models range from 2.53% to 22.00%, with our model achieving 22.90%. This model has potential for wider applications in anomaly detection, particularly in datasets with irregular time series and complex customer relationships. © 2024 Elsevier Ltd | H39: Scopus | I39: =IF(B39="","",IF(AND(F39<>"",SUMPRODUCT(--ISNUMBER(SEARCH(Preseleccionados!$A$2:$A$11,F39)))>0),"YA ESTÁ",IF(AND(F39<>"",COUNTIF($F$3:F39,F39)>1),"REPETIDO",""))) | J39: =IF(OR(B39="",I39<>""),"",IF(MOD(COUNTIFS($B$3:B39,"<>",$I$3:I39,""),2)=1,"Carlos","Joaquín")) | K39: Sigue | L39: Sigue | P39: =IF(J39="","",IF(K39="Sale","Descartado",IF(L39="Sale","Descartado",IF(OR(M39="Q3",M39="Q4",M39="No aparece"),"Descartado",IF(N39="Sale","Descartado",IF(O39="Sigue","APROBADO","En proceso")))))) | Q39: Department of Computer Science, Yang Ming Chiao Tung University, No. 1001, Daxue Rd., Hsinchu, 300093, Taiwan; Department of Information Management and Finance, Yang Ming Chiao Tung University, No. 1001, Daxue Rd., Hsinchu, 300093, Taiwan; Risk and Insurance Research Center, National Chengchi University, No. 64, Sec. 2, Zhinan Rd., Wenshan Dist., Taipei, 11605, Taiwan; School of Information Engineering, Xiamen Ocean Vocational College, No. 61 Tiyu Rd, Fujian, Xiamen, 361012, China | R39: Bancos
A40: =IF(B40="","",ROW()-2) | B40: Mitigating Class Imbalance in Banking Transactions: A Graph-Based GAN Solution for Fraud Detection | C40: K K G.; B V A.; Reddy H.P.; Mayur N.R.; Bhowmik B. | D40: 2026 | E40: Computational Economics | F40: 10.1007/s10614-025-11219-1 | G40: In an era of complex digital transactions, financial fraud detection remains a critical challenge for institutions worldwide. Financial datasets are often highly imbalanced, with fraudulent transactions constituting only a small fraction of the overall volume. This imbalance hinders machine learning models, leading to diminished accuracy in identifying minority-class instances. To address this issue, this paper provides a comprehensive comparative analysis of various class imbalance adjusting schemes—including resampling, cost-sensitive, and ensemble methods—and highlights their respective limitations in handling complex transactional data. Building on these insights, the paper proposes a novel approach that integrates Conditional Generative Adversarial Networks (CGAN) with Graph Attention Networks (GAT). The CGAN+GAT framework synthesizes high-fidelity minority-class samples while preserving the intricate relational structures inherent in financial transactions. Extensive experiments on the IBM Transactions for Anti-Money Laundering (AML) dataset demonstrate that CGAN+GAT outperforms traditional resampling methods, cost-sensitive approaches, and baseline graph-based models in both statistical fidelity and classification performance. Evaluation metrics, including accuracy, F1-score, and G-Mean, indicate that the CGAN+GAT approach achieves superior detection rates, significantly reducing false negatives. This research underscores the importance of combining generative modeling with graph-based attention mechanisms to enhance fraud detection in highly imbalanced, complex financial datasets. © The Author(s), under exclusive licence to Springer Science+Business Media, LLC, part of Springer Nature 2026. | H40: Scopus | I40: =IF(B40="","",IF(AND(F40<>"",SUMPRODUCT(--ISNUMBER(SEARCH(Preseleccionados!$A$2:$A$11,F40)))>0),"YA ESTÁ",IF(AND(F40<>"",COUNTIF($F$3:F40,F40)>1),"REPETIDO",""))) | J40: =IF(OR(B40="",I40<>""),"",IF(MOD(COUNTIFS($B$3:B40,"<>",$I$3:I40,""),2)=1,"Carlos","Joaquín")) | P40: =IF(J40="","",IF(K40="Sale","Descartado",IF(L40="Sale","Descartado",IF(OR(M40="Q3",M40="Q4",M40="No aparece"),"Descartado",IF(N40="Sale","Descartado",IF(O40="Sigue","APROBADO","En proceso")))))) | Q40: Ishwarchandra Vidyasagar AIT Lab, BRICS Laboratory, Department of Computer Science Engineering, National Institute of Technology Karnataka, Surathkal, Karnataka, Mangalore, 575025, India | R40: Bancos
A41: =IF(B41="","",ROW()-2) | B41: Detection of abnormal transaction using spatial ontology-based deep learning approach | C41: Sambandam P. | D41: 2025 | E41: Knowledge and Information Systems | F41: 10.1007/s10115-025-02579-z | G41: Spatial ontology is one of the significant techniques for detecting suspicious transactions in financial institutions. This work proposes an expert system via spatial ontology-based Deep learning for effectively detecting abnormal transactions. The proposed methodology has the stages like pre-processing, construction of ontology and transaction detection. The initial step is pre-processing, during which specific data items are converted into ontology format and noisy data is eliminated. Next, a set of semantic web rule languages and a knowledge base are incorporated into the construction of ontology. New knowledge is gathered from the predefined rules using native reasoning to assist in ontology about every transaction. The proposed method uses a stacked autoencoder (SAE), a deep learning technique, to classify normal and abnormal transactions, and it is trained on the deduced knowledge base. After the classification process, the abnormal transaction list is provided to the query inferred to obtain different information from that list. The experimental analysis is carried out on the two benchmark datasets, synthetic financial and credit card datasets, and compared with the existing approaches. The accuracy obtained by the proposed model for synthetic financial and credit card datasets is 93% and 96.23%, respectively. The experimental results showed that the proposed system performed better than the state-of-the-art approaches. © The Author(s), under exclusive licence to Springer-Verlag London Ltd., part of Springer Nature 2025. | H41: Scopus | I41: =IF(B41="","",IF(AND(F41<>"",SUMPRODUCT(--ISNUMBER(SEARCH(Preseleccionados!$A$2:$A$11,F41)))>0),"YA ESTÁ",IF(AND(F41<>"",COUNTIF($F$3:F41,F41)>1),"REPETIDO",""))) | J41: =IF(OR(B41="",I41<>""),"",IF(MOD(COUNTIFS($B$3:B41,"<>",$I$3:I41,""),2)=1,"Carlos","Joaquín")) | K41: Sigue | L41: Sigue | P41: =IF(J41="","",IF(K41="Sale","Descartado",IF(L41="Sale","Descartado",IF(OR(M41="Q3",M41="Q4",M41="No aparece"),"Descartado",IF(N41="Sale","Descartado",IF(O41="Sigue","APROBADO","En proceso")))))) | Q41: Department of Computer Science and Business Systems, Easwari Engineering College, Ramapuram, Tamilnadu, Chennai, India | R41: Bancos
A42: =IF(B42="","",ROW()-2) | B42: Banking resilience in the era of dual AI risk-adoption gap analysis and strategic implications for global AFC | C42: Trifiletti M. | D42: 2026 | E42: Journal of Risk Management in Financial Institutions | F42: 10.69554/LTAS4306 | G42: This paper examines how the global banking sector preserves resilience under a dual technological shock: the criminal use of generative artificial intelligence (GenAI) and agentic AI1 in money laundering, fraud, and sanctions evasion, and the slow deployment of defensive AI/ machine learning (ML) in anti-money laundering (AML)/anti-financial crime (AFC) programmes. It tests the hypothesis of a systemic ‘risk-adoption gap’ between the speed of threat evolution and the industrialisation of defensive AI. A qualitative triangulation integrates (1) the Association of Certified Anti-Money Laundering Specialists (ACAMS) Global AFC Threats Report 2025;2 (2) quantitative evidence from ‘Global AML Research: The Road to Integration’ (SAS–ACAMS–KPMG, 2024); (3) Financial Action Task Force standards on digital transformation and virtual assets; and (4) Europol and Cybercrime Trends 2025 analyses on AI-enabled cybercrime. Cross-source patterns inform policy implications. The study finds that only 18 per cent of institutions have fully operational AI/ML in AML/counter-terrorism financing, while 40 per cent lack any adoption plan, despite AI-driven threats rated high/very high. Legacy IT and data constraints and a talent gap in data/ML/explainable AI (XAI) are the main internal barriers. Asia combines high AI use with fragile infrastructures, whereas the US/Oceania show delays linked to regulation and core-system complexity. Offensively, GenAI amplifies authorised push payment and document fraud, synthetic identities and multi-channel phishing, eroding rule-based controls. Non-homogeneous data sources limit statistical generalisation but enable framing AFC 5.0 as asymmetric warfare, where AI powers both crime and defence. The paper formalises the risk-adoption gap as a driver of systemic stability, aligns AI-enabled threats, banks’ AI/ML maturity and regulation, and outlines a resilience architecture grounded in data, governance, and talent. This article is also included in The Business & Management Collection which can be accessed at https://hstalks.com/ business/. © Henry Stewart Publications 1752-8895 (2026). | H42: Scopus | I42: =IF(B42="","",IF(AND(F42<>"",SUMPRODUCT(--ISNUMBER(SEARCH(Preseleccionados!$A$2:$A$11,F42)))>0),"YA ESTÁ",IF(AND(F42<>"",COUNTIF($F$3:F42,F42)>1),"REPETIDO",""))) | J42: =IF(OR(B42="",I42<>""),"",IF(MOD(COUNTIFS($B$3:B42,"<>",$I$3:I42,""),2)=1,"Carlos","Joaquín")) | P42: =IF(J42="","",IF(K42="Sale","Descartado",IF(L42="Sale","Descartado",IF(OR(M42="Q3",M42="Q4",M42="No aparece"),"Descartado",IF(N42="Sale","Descartado",IF(O42="Sigue","APROBADO","En proceso")))))) | Q42: Department of Social Sciences, Universidad Católica de Murcia, Murcia, Spain; international financial institution, Spain | R42: Bancos
A43: =IF(B43="","",ROW()-2) | B43: The use of predictive modeling to identify relevant features for suspicious activity reporting | C43: Hayble-Gomes E. | D43: 2023 | E43: Journal of Money Laundering Control | F43: 10.1108/JMLC-02-2022-0034 | G43: Purpose: The purpose of this study is to explore and use artificial intelligence (AI) techniques for identifying the relevant attributes necessary to file a suspicious activity report (SAR) using historical customer transactions. This method is known as predictive modeling, a statistical approach which uses machine learning algorithm to predict outcomes by using historical data. The models are applied to a modified data set designed to mimic transactions of retail banking within the USA. Design/methodology/approach: Machine learning classifiers, as a subset of AI, are trained using transactions that meet or exceed the minimum threshold amount that could generate an alert and report a SAR to the government authorities. The predictive models are developed to use customer transactional data to predict the probability that a transaction is reportable. Findings: The performance of the machine learning classifiers is determined in terms of accuracy, misclassification, true positive rate, false positive rate and false negative rate. The decision tree model provided insight in terms of the attributes relevant for SAR filing based on the rule-based criteria of the algorithm. Originality/value: This research is part of emerging studies in the field of compliance where AI/machine learning technology is used for transaction monitoring to identify relevant attributes for suspicious activity reporting. The research methodology may be replicated by other researchers, Bank Secrecy Act/anti-money laundering (BSA/AML) officers and model validation analysts for BSA/AML compliance models. © 2022, Emerald Publishing Limited. | H43: Scopus | I43: =IF(B43="","",IF(AND(F43<>"",SUMPRODUCT(--ISNUMBER(SEARCH(Preseleccionados!$A$2:$A$11,F43)))>0),"YA ESTÁ",IF(AND(F43<>"",COUNTIF($F$3:F43,F43)>1),"REPETIDO",""))) | J43: =IF(OR(B43="",I43<>""),"",IF(MOD(COUNTIFS($B$3:B43,"<>",$I$3:I43,""),2)=1,"Carlos","Joaquín")) | K43: Sigue | L43: Sigue | P43: =IF(J43="","",IF(K43="Sale","Descartado",IF(L43="Sale","Descartado",IF(OR(M43="Q3",M43="Q4",M43="No aparece"),"Descartado",IF(N43="Sale","Descartado",IF(O43="Sigue","APROBADO","En proceso")))))) | Q43: Department of Artificial Intelligence, Capitol Technology University, Laurel, MD, United States | R43: Bancos
A44: =IF(B44="","",ROW()-2) | B44: Research on intelligent optimization mechanisms of financial process modules through Machine Learning-enhanced collaborative systems in digital finance platforms | C44: Wang T.; Tobias G.R. | D44: 2025 | E44: Future Technology | F44: 10.55670/fpll.futech.4.4.20 | G44: This research addresses the critical need for intelligent optimization mechanisms in financial process modules by developing a machine learning-enhanced collaborative system designed for digital finance platforms, aiming to bridge theoretical advances in human-machine collaboration with practical applications in financial process optimization. A sophisticated multi-layered architecture integrating machine learning capabilities with human decision-making processes was developed, incorporating advanced ensemble algorithms, multi-objective optimization techniques, and adaptive learning mechanisms. The system was validated across three real-world scenarios. These included credit risk assessment using 2.26 million Lending Club records, anti-money laundering with 6.3 million FinCEN transactions, and customer service optimization with 1.8 million banking interactions. The collaborative system achieved significant improvements. Cost reduced by 28.4% and accuracy increased by 15.3% in credit risk assessment. AML efficiency improved by 256%, and AUC-ROC increased from 0.847 to 0.923. Processing time was reduced from 4.2 days to 1.8 days while maintaining regulatory compliance, resulting in a 44.8% return on investment in the first operational year. The learning collaborative approach efficiently combines human knowledge and AI, outperforming regular computerized methods as well as purely human strategies and maintaining long-term system improvement through its adaptive learning capability. This study provides practical toolkits for financial institutions to further explore AI in process optimization, aiming to achieve sustainable competitive advantages and compliance, while also ensuring operational efficiencies. © 2025, Future Publishing LLC. All rights reserved. | H44: Scopus | I44: =IF(B44="","",IF(AND(F44<>"",SUMPRODUCT(--ISNUMBER(SEARCH(Preseleccionados!$A$2:$A$11,F44)))>0),"YA ESTÁ",IF(AND(F44<>"",COUNTIF($F$3:F44,F44)>1),"REPETIDO",""))) | J44: =IF(OR(B44="",I44<>""),"",IF(MOD(COUNTIFS($B$3:B44,"<>",$I$3:I44,""),2)=1,"Carlos","Joaquín")) | P44: =IF(J44="","",IF(K44="Sale","Descartado",IF(L44="Sale","Descartado",IF(OR(M44="Q3",M44="Q4",M44="No aparece"),"Descartado",IF(N44="Sale","Descartado",IF(O44="Sigue","APROBADO","En proceso")))))) | Q44: College of Business Administration, University of the Cordilleras, Gov. Pack Road, Baguio City, 2600, Philippines | R44: Bancos
A45: =IF(B45="","",ROW()-2) | B45: Benefits and risks of the application of artificial intelligence in central bank operations; [Возможности и риски применения искусственного интеллекта в деятельности центральных банков] | C45: Kochergin D.A. | D45: 2026 | E45: Terra Economicus | F45: 10.18522/2073-6606-2026-24-2-101-116 | G45: The article deals with the opportunities and risks associated with the implementation of artificial intelligence technologies in central banks. The study examines the key concepts and elements of the artificial intelligence hierarchy, identifies the most promising areas for the application of generative artificial intelligence in central bank operations, highlights the risks associated with the implementation of artificial intelligence, and proposes methods to minimize them. The study found that the main contemporary cases for artificial intelligence use in central banks involve: economic analysis and forecasting, improving the functioning of payment systems, regulation, supervision, and control over the activities of financial institutions, detection of information anomalies, and risk assessment. It has been established that the use of artificial intelligence technologies in central banking operations can enhance the effectiveness of anti-money laundering efforts, strengthen cybersecurity, and support the fulfillment of mandates related to price and financial stability. At the same time, the adoption of such technologies may create new sources of operational, reputational, and model risks, as well as risks related to data privacy, which requires the establishment of an adequate risk management system. Adapting existing risk management models to artificial intelligence projects based on a multi-layered defense approach, along with the comprehensive implementation of measures to minimize the negative consequences of artificial intelligence adoption, can facilitate its implementation across various areas of central bank operations. © Д.А. Кочергин, 2026 | H45: Scopus | I45: =IF(B45="","",IF(AND(F45<>"",SUMPRODUCT(--ISNUMBER(SEARCH(Preseleccionados!$A$2:$A$11,F45)))>0),"YA ESTÁ",IF(AND(F45<>"",COUNTIF($F$3:F45,F45)>1),"REPETIDO",""))) | J45: =IF(OR(B45="",I45<>""),"",IF(MOD(COUNTIFS($B$3:B45,"<>",$I$3:I45,""),2)=1,"Carlos","Joaquín")) | K45: Sale | P45: =IF(J45="","",IF(K45="Sale","Descartado",IF(L45="Sale","Descartado",IF(OR(M45="Q3",M45="Q4",M45="No aparece"),"Descartado",IF(N45="Sale","Descartado",IF(O45="Sigue","APROBADO","En proceso")))))) | Q45: Institute of Economics RAS, Moscow, Russian Federation | R45: Bancos
A46: =IF(B46="","",ROW()-2) | B46: Detecting Hawala network for money laundering by graph mining | C46: Alenova M.; Utaliyeva A.; Li K.-J. | D46: 2024 | E46: Journal of Finance and Data Science | F46: 10.1016/j.jfds.2024.100147 | G46: Hawala, a traditional but informal money transfer system, has been prevalent in many parts of the world, such as money laundering. Despite the regulatory actions taken by financial institutions, Hawala is still a key node in terror financing schemes and its extent of misuse is unknown. Due to the hidden transactions and limited knowledge about the Hawala, it is difficult for legal enforcement authorities such as financial intelligence units (FIU) of each country to detect and investigate the Hawala network. In this paper, we present a novel approach to detect the potential Hawala instances in the stream of financial transaction data by using graph mining techniques. In order to reflect the properties of Hawala, we apply graph mining methods such as graph centrality, Blackhole metric, and Hidden link metric as well as anomaly detection methods using graph convolutional network. Experiments demonstrate that the proposed method gives a meaningful result in detecting Hawala network and can be used as a complementary tool to the existing transactional monitoring tracks. © 2024 The Authors | H46: Scopus | I46: =IF(B46="","",IF(AND(F46<>"",SUMPRODUCT(--ISNUMBER(SEARCH(Preseleccionados!$A$2:$A$11,F46)))>0),"YA ESTÁ",IF(AND(F46<>"",COUNTIF($F$3:F46,F46)>1),"REPETIDO",""))) | J46: =IF(OR(B46="",I46<>""),"",IF(MOD(COUNTIFS($B$3:B46,"<>",$I$3:I46,""),2)=1,"Carlos","Joaquín")) | P46: =IF(J46="","",IF(K46="Sale","Descartado",IF(L46="Sale","Descartado",IF(OR(M46="Q3",M46="Q4",M46="No aparece"),"Descartado",IF(N46="Sale","Descartado",IF(O46="Sigue","APROBADO","En proceso")))))) | Q46: Pusan National University, Department of Computer Science and Engineering, Busan, Busan, 46241, South Korea | R46: Bancos
A47: =IF(B47="","",ROW()-2) | B47: Accounting scripts and the politics of compliance: Understanding accountants’ roles in anti-money laundering through sentiment and script theory | C47: Lokanan M.E. | D47: 2026 | E47: Journal of Economic Criminology | F47: 10.1016/j.jeconc.2026.100207 | G47: This study explores the role of accountants in anti-money laundering (AML) compliance within Canada's non-banking financial institutions, specifically focusing on the real estate, luxury vehicles, and gaming sectors. By utilizing a unique combination of machine learning (ML) and deep learning (DL) algorithms, along with natural language processing techniques, the research conducts sentiment analysis on the testimonies of accountants who appeared at the Cullen Commission inquiry. Supported by semi-structured interviews with key gatekeepers, this study provides a comprehensive understanding of accountants' perspectives and experiences in AML compliance. The sentiment analysis, utilizing both ML and DL models, reveals a predominance of positive sentiments among the testimonies, indicating overall satisfaction with regulatory frameworks and participation in AML initiatives. Neutral sentiments emphasize the provision of factual descriptions of procedures and regulations, while negative sentiments highlight concerns regarding the effectiveness of AML measures. Applying script theory as a cognitive framework, the study categorizes accountants' cognitive processing into three stages: preexisting schemata, assimilation, and accommodation. These stages illustrate the progression of accountants' perspectives and strategies in response to AML compliance challenges, ranging from reliance on previous experiences and beliefs to the integration of new information and adjustment to regulatory changes. The findings offer fresh insights into the field of accounting scholarship, particularly in critical accounting research. The utilization of advanced DL methods in sentiment analysis represents a methodological innovation, allowing for a deeper comprehension of accountants' roles in AML compliance. © 2026 | H47: Scopus | I47: =IF(B47="","",IF(AND(F47<>"",SUMPRODUCT(--ISNUMBER(SEARCH(Preseleccionados!$A$2:$A$11,F47)))>0),"YA ESTÁ",IF(AND(F47<>"",COUNTIF($F$3:F47,F47)>1),"REPETIDO",""))) | J47: =IF(OR(B47="",I47<>""),"",IF(MOD(COUNTIFS($B$3:B47,"<>",$I$3:I47,""),2)=1,"Carlos","Joaquín")) | K47: Sale | P47: =IF(J47="","",IF(K47="Sale","Descartado",IF(L47="Sale","Descartado",IF(OR(M47="Q3",M47="Q4",M47="No aparece"),"Descartado",IF(N47="Sale","Descartado",IF(O47="Sigue","APROBADO","En proceso")))))) | Q47: Faculty of Management, Royal Roads University, 2005 Sooke Road, Victoria, V9B 5Y2, BC, Canada | R47: Bancos
A48: =IF(B48="","",ROW()-2) | B48: Anti-Money Laundering by Group-Aware Deep Graph Learning | C48: Cheng D.; Ye Y.; Xiang S.; Ma Z.; Zhang Y.; Jiang C. | D48: 2023 | E48: IEEE Transactions on Knowledge and Data Engineering | F48: 10.1109/TKDE.2023.3272396 | G48: Anti-money laundering (AML) is a classical data mining problem in finance applications. As well known, money laundering (ML) is critical to the effective operation of transnational and organized crime, which affects a country's economy, government, and social wellbeings. Financial services organizations facilitate the movement of money and have been enlisted by governments to assist with the detection and prevention of money laundering, which is a key tool in the fight to reduce crime and create sustainable economic development. In the application of AML, user identity and financial behavior data are widely used to detect laundering transactions. In recent years, an increasing number of money laundering activities have been conducted by organized criminal gangs while most existing works still treat the actions of each account as independent identity behavior without considering the group-level conspired interactions. Therefore, in this paper, we propose a group-aware deep graph learning-based approach for organized money-laundering detection. In particular, we design a community-centric encoder to represent the nodes and attributes in user transaction graphs and derive the adjacent gang behaviors. Then, we devise a scheme of local enhancement to accommodate nodes with similar transaction features, which are aggregated into gangs for downstream detection. Extensive experiments on the real-world dataset from one of the largest bank card alliances worldwide show that our proposed method outperforms state-of-the-art methods in both offline and online modes, showing the effectiveness of money laundering detection with group-aware deep graph learning. © 1989-2012 IEEE. | H48: Scopus | I48: =IF(B48="","",IF(AND(F48<>"",SUMPRODUCT(--ISNUMBER(SEARCH(Preseleccionados!$A$2:$A$11,F48)))>0),"YA ESTÁ",IF(AND(F48<>"",COUNTIF($F$3:F48,F48)>1),"REPETIDO",""))) | J48: =IF(OR(B48="",I48<>""),"",IF(MOD(COUNTIFS($B$3:B48,"<>",$I$3:I48,""),2)=1,"Carlos","Joaquín")) | P48: =IF(J48="","",IF(K48="Sale","Descartado",IF(L48="Sale","Descartado",IF(OR(M48="Q3",M48="Q4",M48="No aparece"),"Descartado",IF(N48="Sale","Descartado",IF(O48="Sigue","APROBADO","En proceso")))))) | Q48: Tongji University, Department of Computer Science and Technology, Shanghai, 201804, China; Shanghai Artificial Intelligence Laboratory, Shanghai, 200030, China; Zhejiang Gongshang University, School of Computer and Information Engineering, Hangzhou, 314423, China; University of Technology Sydney, Australian Artificial Intelligence Institute, Sydney, 2007, NSW, Australia; China UnionPay Company, Ltd., Research and Development Center of Financial Safety, Shanghai, 201201, China | R48: Bancos
A49: =IF(B49="","",ROW()-2) | B49: Automatic suppression of false positive alerts in anti-money laundering systems using machine learning | C49: Bakry A.N.; Alsharkawy A.S.; Farag M.S.; Raslan K.R. | D49: 2024 | E49: Journal of Supercomputing | F49: 10.1007/s11227-023-05708-z | G49: Criminal activities generate an estimated $2 trillion in laundered money per year, highlighting the need for financial institutions to detect and report suspicious activity to protect their reputation. However, rule-based models commonly used for this purpose generate a high number of false positives, draining compliance team time, and increasing investigation costs. However, the application of machine learning in conjunction with rule-based models presents noteworthy implications, encompassing the potential reduction in false positives and the concomitant risk of machine learning inadvertently suppressing true positive alerts. This paper proposes a framework called automatic suppression based on XGBoost for anti-money laundering (ASXAML) to enhance detection by reducing false positives. ASXAML leverages recursive feature elimination with cross-validation for optimal feature selection. Subsequently, Optuna is employed to fine-tune hyperparameters for the XGBoost model. Results indicate that ASXAML achieves an optimal balance between reducing false positives and avoiding missed money laundering events, with an 86% F-beta score and only 11% money laundering customers were incorrectly closed out of 1926 in the test data. © The Author(s) 2023. | H49: Scopus | I49: =IF(B49="","",IF(AND(F49<>"",SUMPRODUCT(--ISNUMBER(SEARCH(Preseleccionados!$A$2:$A$11,F49)))>0),"YA ESTÁ",IF(AND(F49<>"",COUNTIF($F$3:F49,F49)>1),"REPETIDO",""))) | J49: =IF(OR(B49="",I49<>""),"",IF(MOD(COUNTIFS($B$3:B49,"<>",$I$3:I49,""),2)=1,"Carlos","Joaquín")) | P49: =IF(J49="","",IF(K49="Sale","Descartado",IF(L49="Sale","Descartado",IF(OR(M49="Q3",M49="Q4",M49="No aparece"),"Descartado",IF(N49="Sale","Descartado",IF(O49="Sigue","APROBADO","En proceso")))))) | Q49: Department of Mathematics, Faculty of Science, Al-Azhar University, Cairo, Nasr City, Egypt | R49: Bancos
A50: =IF(B50="","",ROW()-2) | B50: Intelligent money laundering detection approaches in banking and E-wallets: a comprehensive survey | C50: Kadamathikuttiyil Karthikeyan G.; Bhowmik B. | D50: 2025 | E50: Journal of Computational Social Science | F50: 10.1007/s42001-025-00421-8 | G50: The rapid evolution of financial technologies (FinTech) has propelled the world into a more dynamic and sophisticated digital financial landscape. This transformation has significantly expanded financial inclusion, offering new opportunities to individuals who were previously excluded from or had limited access to traditional banking services. Financial inclusion is crucial as it provides access to a broad spectrum of financial services, including bank accounts, credit and debit facilities, and e-wallets. While the rise in digital transactions has been driven by cost efficiency, convenience, and enhanced security measures, it has also led to an increase in economic crimes, particularly money laundering, resulting in substantial global economic losses. Consequently, the need for effective strategies to combat money laundering has never been more pressing. This study thoroughly investigates the state-of-the-art techniques in money laundering detection harnessing the capabilities of artificial intelligence (AI) technologies. First, we provide an overview of economic crimes and classify their various types, setting the stage for a focused discussion on money laundering. The paper then explores the money laundering landscape, including its impact and recent trends, followed by a discussion on different prevention and detection strategies. The paper also delves into AI-driven detection strategies, particularly those targeting money laundering, including the detection of laundering activities through e-wallets. Additionally, we address the research challenges associated with money laundering detection, such as the issue of class imbalance in financial datasets, and propose solutions to overcome it. Finally, the paper provides insights into future directions for research, aiming to equip the research community with the tools necessary to formulate proactive strategies for preventing and mitigating money laundering and related economic crimes. © The Author(s), under exclusive licence to Springer Nature Singapore Pte Ltd. 2025. | H50: Scopus | I50: =IF(B50="","",IF(AND(F50<>"",SUMPRODUCT(--ISNUMBER(SEARCH(Preseleccionados!$A$2:$A$11,F50)))>0),"YA ESTÁ",IF(AND(F50<>"",COUNTIF($F$3:F50,F50)>1),"REPETIDO",""))) | J50: =IF(OR(B50="",I50<>""),"",IF(MOD(COUNTIFS($B$3:B50,"<>",$I$3:I50,""),2)=1,"Carlos","Joaquín")) | K50: Sale | P50: =IF(J50="","",IF(K50="Sale","Descartado",IF(L50="Sale","Descartado",IF(OR(M50="Q3",M50="Q4",M50="No aparece"),"Descartado",IF(N50="Sale","Descartado",IF(O50="Sigue","APROBADO","En proceso")))))) | Q50: Ishwarchandra Vidyasagar AIT Lab, BRICS Laboratory, Department of Computer Science Engineering, National Institute of Technology Karnataka, Surathkal, Karnataka, Mangalore, 575025, India | R50: Bancos
A51: =IF(B51="","",ROW()-2) | B51: Intelligent information systems of the banking sector: General characteristics and information environment | C51: Prymostka L.; Kysil T. | D51: 2023 | E51: Scientific Bulletin of Mukachevo State University. Series Economics | F51: 10.52566/msu-econ4.2023.43 | G51: Due to the rapid development of digitalization and information technology, the study of intelligent information systems (IIS) in the banking sector is becoming an urgent task. Intelligent information systems are able to optimize banking processes, increase security, improve the quality of customer service, mitigate risks, and optimize internal processes of financial stability management. The purpose of this study is to reveal the potential and impact of IIS on banking management processes; to study their capabilities. To achieve this goal, this study used an analytical approach, in particular, methods of information and morphological data analysis, as well as the method of generalization, which allowed the identification of key aspects, features, and properties of intelligent information systems of the banking sector, and to provide a generalized structure of their functioning by the relevant processes. This article generalizes a group of intelligent information systems of the banking sector (IISBS), their general features and properties, proposes an innovative architecture of financial management support, and identifies their advantages in comparison with existing intelligent systems. The study proves that intelligent information systems of the banking sector are endowed with hybrid data analytics provided by deep learning methods using self-learning algorithms; are able to assess possible risks and plan strategies for their resolution; recognize unauthorized entries and suspicious transactions; thanks to virtual assistants, are suitable for robotizing management processes; and visually present the results of analysing large amounts of data in real time. The research conducted in this paper shows that the introduction of intelligent information systems in the banking sector is of high practical value, as it provides interactivity and personalization for customers, online interaction, and support in solving problems through various communication channels. © The Author(s). | H51: Scopus | I51: =IF(B51="","",IF(AND(F51<>"",SUMPRODUCT(--ISNUMBER(SEARCH(Preseleccionados!$A$2:$A$11,F51)))>0),"YA ESTÁ",IF(AND(F51<>"",COUNTIF($F$3:F51,F51)>1),"REPETIDO",""))) | J51: =IF(OR(B51="",I51<>""),"",IF(MOD(COUNTIFS($B$3:B51,"<>",$I$3:I51,""),2)=1,"Carlos","Joaquín")) | P51: =IF(J51="","",IF(K51="Sale","Descartado",IF(L51="Sale","Descartado",IF(OR(M51="Q3",M51="Q4",M51="No aparece"),"Descartado",IF(N51="Sale","Descartado",IF(O51="Sigue","APROBADO","En proceso")))))) | Q51: Kyiv National Economic University named after Vadym Hetman, 54/1 Peremohy Ave, Kyiv, 03057, Ukraine | R51: Bancos
A52: =IF(B52="","",ROW()-2) | B52: Evaluating fraud detection algorithms in a decentralized scenario | C52: Gige A.M.; Buschmann Alsbirk L.; Coscia M. | D52: 2026 | E52: Royal Society Open Science | F52: 10.1098/rsos.251922 | G52: Financial fraud is an umbrella term including a vast number of illegal activities. These activities involve a significant fraction of the global economy. Traditional investigation techniques are labour-intensive and cannot scale to match the size of the issue. Machine learning has provided effective tools which deliver high accuracy in identifying transactions that could be involved in fraudulent activities. In this paper, we point out that the state-of-the-art in financial fraud detection has been applied to the unrealistic scenario of an omniscient centralized global authority which has access to all bank transactions globally. We propose a more realistic evaluation scenario, one made of two steps: first, the bank flags its own transactions using exclusively information it possesses; then only flagged transactions from all banks are analysed by the governmental authority for potential prosecution. We find that, in such a realistic scenario, the effectiveness of the state-of-the-art method for financial fraud detection decreases. Moreover, we show that in this decentralized scenario, it pays off to use simpler methods than the state-of-the-art, depending on the specific objective function the system wants to ensure. © 2026 The Authors. | H52: Scopus | I52: =IF(B52="","",IF(AND(F52<>"",SUMPRODUCT(--ISNUMBER(SEARCH(Preseleccionados!$A$2:$A$11,F52)))>0),"YA ESTÁ",IF(AND(F52<>"",COUNTIF($F$3:F52,F52)>1),"REPETIDO",""))) | J52: =IF(OR(B52="",I52<>""),"",IF(MOD(COUNTIFS($B$3:B52,"<>",$I$3:I52,""),2)=1,"Carlos","Joaquín")) | K52: Sigue | L52: Sigue | P52: =IF(J52="","",IF(K52="Sale","Descartado",IF(L52="Sale","Descartado",IF(OR(M52="Q3",M52="Q4",M52="No aparece"),"Descartado",IF(N52="Sale","Descartado",IF(O52="Sigue","APROBADO","En proceso")))))) | Q52: IT University of Copenhagen, Copenhagen, Denmark | R52: Bancos
A53: =IF(B53="","",ROW()-2) | B53: Transaction monitoring in anti-money laundering: A qualitative analysis and points of view from industry | C53: Oztas B.; Cetinkaya D.; Adedoyin F.; Budka M.; Aksu G.; Dogan H. | D53: 2024 | E53: Future Generation Computer Systems | F53: 10.1016/j.future.2024.05.027 | G53: Financial institutions face significant challenges in their efforts to prevent money laundering and terrorist financing due to criminals’ continuously evolving techniques and the vast volume of transactions that need to be processed. The traditional rules-based methods utilised in banks produce high false positive rates, which lead to increased costs and inefficiencies. This study identified the perspectives of 8 anti-money laundering (AML) specialists on the current state and potential improvements in transaction monitoring methods. The results provide in-depth knowledge of the problems and requirements for researchers and practitioners. Semi-structured interviews conducted with the AML experts (totalling 480 min) identified the challenges, requirements for successful implementation, and future trends in transaction monitoring. The findings reveal a growing interest in machine learning and artificial intelligence to enhance the efficiency and accuracy of current approaches. Furthermore, innovative methods such as graph analysis and anomaly detection were suggested to overcome the limitations of rule-based systems. Requirements such as explainability, flexibility, and identifying new risks were extracted and analysed. This research contributes to the existing literature by providing valuable insights from industry experts, guiding the development of advanced transaction monitoring methods, and addressing the disconnect and lack of studies between industries and academicians in the domain. © 2024 The Authors | H53: Scopus | I53: =IF(B53="","",IF(AND(F53<>"",SUMPRODUCT(--ISNUMBER(SEARCH(Preseleccionados!$A$2:$A$11,F53)))>0),"YA ESTÁ",IF(AND(F53<>"",COUNTIF($F$3:F53,F53)>1),"REPETIDO",""))) | J53: =IF(OR(B53="",I53<>""),"",IF(MOD(COUNTIFS($B$3:B53,"<>",$I$3:I53,""),2)=1,"Carlos","Joaquín")) | P53: =IF(J53="","",IF(K53="Sale","Descartado",IF(L53="Sale","Descartado",IF(OR(M53="Q3",M53="Q4",M53="No aparece"),"Descartado",IF(N53="Sale","Descartado",IF(O53="Sigue","APROBADO","En proceso")))))) | Q53: Department of Computing and Informatics, Bournemouth University, Talbot Campus, Poole, Bournemouth, BH12 5BB, United Kingdom; Danske Bank, London, EC4N 7DT, United Kingdom | R53: Bancos
A54: =IF(B54="","",ROW()-2) | B54: Evaluating Risk Management Strategies Using Analytical Frameworks: Multi Method Study Across Industries in U.S. | C54: Islam M.M.; Chy K.S.; Rahman T.; Akter M.; Pranto M.R.H. | D54: 2025 | E54: Dianwang Jishu/Power System Technology | F54: 10.52783/PST.2090 | G54: This study addressed the critical inefficiency of siloed risk management approaches across U.S. industries, where fragmented methodologies for fraud detection (healthcare), AML monitoring (finance), and fiscal forecasting (public sector) incur annual losses exceeding $100 billion. We developed a unified analytical framework integrating machine learning (Isolation Forest, LSTM), network analysis (GNNs), and econometric modeling (ARIMA) to enable cross-sector risk interoperability. The methodology processed: (1) 500,000 anonymized Medicare claims (CMS/RADV), (2) synthetic FinCEN SARs networks emulating money laundering patterns, and (3) CBO macroeconomic indicators, evaluated through multi-criteria validation (precision-recall, MAE, PageRank centrality). Results demonstrated significant improvements over sector-specific baselines: fraud detection achieved 89.7% recall (Δ+27.4%, p<0.01) with SHAP analysis revealing claim frequency and provider networks as top predictive features; AML precision increased by 32.7% through transaction graph clustering (modularity=0.83); fiscal forecast errors reduced by 29.5% via hybrid LSTM-ARIMA modeling. The framework’s interpretability was validated through three lenses: (a) clinical relevance of detected Medicare fraud patterns (OIG audit alignment), (b) AML network topology consistency with FinCEN typologies, and (c) fiscal shock responsiveness within CBO confidence intervals. Economic simulations projected $12.5B annual savings from integrated implementation (ROI 3.6:1), though legacy system integration costs varied by sector (public: +47% vs banking: +71%). The study’s scientific contribution is threefold: (1) a validated protocol for cross-domain risk variable harmonization, (2) demonstration of interpretable AI’s superiority in regulated environments (SHAP-driven false positive reduction), and (3) quantification of cyber-physical risk couplings (fraud-AML volatility r=0.52±0.03). These advancements provide policymakers with a replicable template for national risk infrastructure modernization, particularly in API standardization and adaptive control deployment. © (2025), (Power System Technology Press). All rights reserved. | H54: Scopus | I54: =IF(B54="","",IF(AND(F54<>"",SUMPRODUCT(--ISNUMBER(SEARCH(Preseleccionados!$A$2:$A$11,F54)))>0),"YA ESTÁ",IF(AND(F54<>"",COUNTIF($F$3:F54,F54)>1),"REPETIDO",""))) | J54: =IF(OR(B54="",I54<>""),"",IF(MOD(COUNTIFS($B$3:B54,"<>",$I$3:I54,""),2)=1,"Carlos","Joaquín")) | P54: =IF(J54="","",IF(K54="Sale","Descartado",IF(L54="Sale","Descartado",IF(OR(M54="Q3",M54="Q4",M54="No aparece"),"Descartado",IF(N54="Sale","Descartado",IF(O54="Sigue","APROBADO","En proceso")))))) | Q54: College of Graduate and Professional Studies, Trine University, United States; Department: Management Information Systems, Lamar University, United States; Department, Dahlkemper School of Business, Gannon University, United States; Department: Information Technology and Project Planning Management, ST. Francis College, United States; Department:- Management, ST. Francis College, United States | R54: Bancos
A55: =IF(B55="","",ROW()-2) | B55: Machine Learning and Network Analysis for Cross‑Border Suspicious Transaction Detection: Evidence from the FinCEN Files | C55: Ejime O.M.; Kosemani A.; Onyeorueka S.I.E. | D55: 2026 | E55: IEEE Access | F55: 10.1109/ACCESS.2026.3685103 | G55: Traditional rule‑based anti‑money‑laundering (AML) systems raise far more alerts than humans can plausibly investigate. In the aftermath of the International Consortium of Investigative Journalists’ FinCEN Files revelations, compliance teams and regulators have begun to ask whether a data‑driven approach might allocate scarce attention more effectively. This study presents a holistic framework that combines descriptive statistics, time‑series modelling, geospatial analysis, network science and machine‑learning classification to analyse 4,507 aggregated transaction groups (more than 200,000 individual transaction records) from the FinCEN Files dataset. After cleaning and integrating the data, we explore the heavy‑tailed distribution of suspicious amounts, identify temporal spikes linked to economic crises, map cross‑border corridors between secrecy jurisdictions, quantify centrality in the bank‑to‑bank network, fit an ARIMA model to monthly volumes, and construct a risk‑scoring system. Logistic regression, Random Forest and XGBoost models are benchmarked against unsupervised isolation and one‑class support vector methods. Ensemble models achieve area‑under‑the‑ROC‑curve scores around 0.97–0.98, substantially outperforming rule‑based or unsupervised baselines. Our results demonstrate that network metrics, particularly degree and betweenness centrality—coupled with high‑risk corridor indicators are among the most important predictors of suspicious behaviour. We conclude by situating these findings within the emerging literature on graph neural networks and proposing avenues for continual learning, beneficial ownership integration and cross‑institutional transferability. Overall, the work illustrates that a judicious blend of machine learning and network analysis can reduce false positives and support risk‑based AML supervision. © 2013 IEEE. | H55: Scopus | I55: =IF(B55="","",IF(AND(F55<>"",SUMPRODUCT(--ISNUMBER(SEARCH(Preseleccionados!$A$2:$A$11,F55)))>0),"YA ESTÁ",IF(AND(F55<>"",COUNTIF($F$3:F55,F55)>1),"REPETIDO",""))) | J55: =IF(OR(B55="",I55<>""),"",IF(MOD(COUNTIFS($B$3:B55,"<>",$I$3:I55,""),2)=1,"Carlos","Joaquín")) | K55: Sigue | L55: Sigue | P55: =IF(J55="","",IF(K55="Sale","Descartado",IF(L55="Sale","Descartado",IF(OR(M55="Q3",M55="Q4",M55="No aparece"),"Descartado",IF(N55="Sale","Descartado",IF(O55="Sigue","APROBADO","En proceso")))))) | Q55: University of Salford, Salford Business School, Manchester, United Kingdom; University of Salford, School of Science, Engineering and Environment, Manchester, United Kingdom | R55: Bancos
A56: =IF(B56="","",ROW()-2) | B56: GCF-MLD: Integrated Approach for Money Laundering Detection Using Machine Learning and Graph Network Analysis | C56: Irshad, F; Alkhalifah, T; Alturise, F; Khan, YD | D56: 2024 | E56: Ieee Access | F56: 10.1109/ACCESS.2024.3510115 | G56: Money laundering is a critical issue for financial institutions especially in developing countries and detecting such suspicious activities is a challenging task. The rule-based money laundering detection systems currently being used by the financial institutions rely on pre-defined rules that are often not able to keep up with rapidly changing tactics of money launderers. In this regard, machine learning based approaches have gained attention for detecting suspicious transactions related to money laundering. In this study, we propose a novel approach Graph-Clustering Fusion for Money Laundering Detection (GCF-MLD) combining graph network analysis with clustering methodology to identify suspicious accounts in real-world banking dataset. The results exhibit that the proposed model can be effectively used by the financial institutions to replace current rule-based techniques to significantly improve the efficiency and effectiveness of money laundering detection systems. | H56: Web of Science | I56: =IF(B56="","",IF(AND(F56<>"",SUMPRODUCT(--ISNUMBER(SEARCH(Preseleccionados!$A$2:$A$11,F56)))>0),"YA ESTÁ",IF(AND(F56<>"",COUNTIF($F$3:F56,F56)>1),"REPETIDO",""))) | J56: =IF(OR(B56="",I56<>""),"",IF(MOD(COUNTIFS($B$3:B56,"<>",$I$3:I56,""),2)=1,"Carlos","Joaquín")) | P56: =IF(J56="","",IF(K56="Sale","Descartado",IF(L56="Sale","Descartado",IF(OR(M56="Q3",M56="Q4",M56="No aparece"),"Descartado",IF(N56="Sale","Descartado",IF(O56="Sigue","APROBADO","En proceso")))))) | Q56: [Irshad, Faizan; Khan, Yaser Daanial] Univ Management & Technol, Sch Syst & Technol, Dept Comp Sci, Lahore 54770, Pakistan; [Alkhalifah, Tamim] Qassim Univ, Coll Comp, Dept Comp Engn, Buraydah 52571, Saudi Arabia; [Alturise, Fahad] Qassim Univ, Coll Comp, Dept Cybersecur, Buraydah 52571, Saudi Arabia | R56: Bancos
A57: =IF(B57="","",ROW()-2) | B57: AI culture 'profiling' and anti-money laundering: Efficacy vs ethics | C57: Goodell, JW; Muckley, CB; Neelakantan, P; Ryan, D; Yu, PS | D57: 2025 | E57: International Review Of Financial Analysis | F57: 10.1016/j.irfa.2025.103980 | G57: Using extensive transaction and money laundering detection data, at a globally important financial institution, we investigate the efficacy of including facets of national culture in formulating anti-money laundering predictions. For corporate and individual accounts, Hofstede individualism scores of the country in which a customer is resident, or from which a wire is sent/received, are of first-order importance in the detection of money laundering. When combined with account and transaction data; as well as even a proprietary institutional algorithm, individualism scores continue to determine the models' predictive performances. The efficacy of cultural profiling in money laundering detection underscores the need for stringent and enforced data protection to prohibit its use. This will safeguard the civil right of individuals to privacy and promote financial inclusion. | H57: Web of Science | I57: =IF(B57="","",IF(AND(F57<>"",SUMPRODUCT(--ISNUMBER(SEARCH(Preseleccionados!$A$2:$A$11,F57)))>0),"YA ESTÁ",IF(AND(F57<>"",COUNTIF($F$3:F57,F57)>1),"REPETIDO",""))) | J57: =IF(OR(B57="",I57<>""),"",IF(MOD(COUNTIFS($B$3:B57,"<>",$I$3:I57,""),2)=1,"Carlos","Joaquín")) | P57: =IF(J57="","",IF(K57="Sale","Descartado",IF(L57="Sale","Descartado",IF(OR(M57="Q3",M57="Q4",M57="No aparece"),"Descartado",IF(N57="Sale","Descartado",IF(O57="Sigue","APROBADO","En proceso")))))) | Q57: [Goodell, John W.] Univ Akron, Akron, OH 44325 USA; [Muckley, Cal B.; Yu, Pei-Shan] Univ Coll Dublin, Smurfit Grad Sch Business, Dublin, Ireland; [Muckley, Cal B.; Yu, Pei-Shan] Univ Coll Dublin, Geary Inst, Dublin, Ireland; [Neelakantan, Parvati] Indian Inst Technol Kanpur, Kanpur, India; [Ryan, Darragh] Univ Galway, Sch Nat Sci, NCLA, Phys, Galway, Ireland | R57: Bancos
A58: =IF(B58="","",ROW()-2) | B58: Incorporating machine learning and a risk-based strategy in an anti-money laundering multiagent system | C58: Alexandre, CR; Balsa, J | D58: 2023 | E58: Expert Systems With Applications | F58: 10.1016/j.eswa.2023.119500 | G58: Over the last decade, the international community has become more aware of the danger and harm caused by the practice of the crime of Money Laundering (ML). Organizations to combat this crime were created and the existing laws were expanded and tightened. Complex legislation, combined with the increase in the volume of financial transactions involved in money laundering schemes, motivated research targeting the improvement and automation of the critical processes of detecting, signaling and communicating suspicious clients. The Anti-Money Laundering (AML) activity is strongly impacted and dependent on this process, which has evolved slowly, in part due to its subjectivity and complexity. This article presents the characteristics of a multiagent system that incorporates machine learning and risk components to identify and flag suspicious bank clients. It also seeks to help human specialists in the analysis of suspicious behavior by these clients. The knowledge bases are obtained through data mining over a real database, obtaining for each client a transactional behavior pattern, enriched with specific rules based on legal aspects, and on the expertise of the AML analysts of the financial institution that funds this research. The adopted risk strategy seeks to identify and classify the ML risk level of each flagged client. To evaluate its results, the system analyzed six months of actual transactions. A set of candidate clients was produced and subsequently investigated by the financial institution's AML analysts, who proved a high degree of correctness in the indicated suspicions, including cases that were not flagged by the antecedent systems in execution for decades at the institution. | H58: Web of Science | I58: =IF(B58="","",IF(AND(F58<>"",SUMPRODUCT(--ISNUMBER(SEARCH(Preseleccionados!$A$2:$A$11,F58)))>0),"YA ESTÁ",IF(AND(F58<>"",COUNTIF($F$3:F58,F58)>1),"REPETIDO",""))) | J58: =IF(OR(B58="",I58<>""),"",IF(MOD(COUNTIFS($B$3:B58,"<>",$I$3:I58,""),2)=1,"Carlos","Joaquín")) | P58: =IF(J58="","",IF(K58="Sale","Descartado",IF(L58="Sale","Descartado",IF(OR(M58="Q3",M58="Q4",M58="No aparece"),"Descartado",IF(N58="Sale","Descartado",IF(O58="Sigue","APROBADO","En proceso")))))) | Q58: [Alexandre, Claudio Reginaldo; Balsa, Joao] Univ Lisbon, Fac Ciencias, LASIGE, Edificio C6,Campo Grande, P-1749016 Lisbon, Portugal | R58: Bancos
A59: =IF(B59="","",ROW()-2) | B59: Leveraging artificial intelligence for enhanced anti-money laundering in financial institutions | C59: Premkumar, A; Vidyavathi, K; Sowmya, VL; Alfurhood, BS; Irudayasamy, A; Natarajan, R | D59: 2026 | E59: Discover Computing | F59: 10.1007/s10791-026-10142-9 | G59: Financial institutions continue to face a significant challenge with money laundering and need intelligent, scalable ways to detect illegal financial activity. This paper introduces a machine learning-driven platform for detecting suspicious financial activities in transactional data with a fixed schema, enriched with temporal, behavioral, and financial profile features. Extensive experiments were performed with several popular supervised learning algorithms, including Logistic regression, Decision tree, Random Forest, Gradient Boosting, AdaBoost, K-Nearest Neighbour (KNN), Support vector machine, and Na & iuml;ve Bayes. The Gradient Boosting classifier performed best overall, achieving an Accuracy of 90.59%, a precision of 90.61%, a recall of 90.59%, and an F1-score of 90.60 in balanced detection, with the highest reliability for detecting suspicious financial transactions. It showed better generalization and robust classification performance than the other models, especially in real anti-money laundering problems, where it performed excellently. These results demonstrate that recent artificial intelligence could fortify anti-money laundering systems by automating and improving the detection of high-risk financial activity. The framework provides a scalable and feasible approach to ensure compliance, manage risk, and secure finances for larger organizations. | H59: Web of Science | I59: =IF(B59="","",IF(AND(F59<>"",SUMPRODUCT(--ISNUMBER(SEARCH(Preseleccionados!$A$2:$A$11,F59)))>0),"YA ESTÁ",IF(AND(F59<>"",COUNTIF($F$3:F59,F59)>1),"REPETIDO",""))) | J59: =IF(OR(B59="",I59<>""),"",IF(MOD(COUNTIFS($B$3:B59,"<>",$I$3:I59,""),2)=1,"Carlos","Joaquín")) | P59: =IF(J59="","",IF(K59="Sale","Descartado",IF(L59="Sale","Descartado",IF(OR(M59="Q3",M59="Q4",M59="No aparece"),"Descartado",IF(N59="Sale","Descartado",IF(O59="Sigue","APROBADO","En proceso")))))) | Q59: [Premkumar, Anitha] Manipal Acad Higher Educ, Manipal Inst Technol Bengaluru, Manipal, India; [Vidyavathi, K.] Selvam Coll Technol, Elect & Commun Engn Dept, Salem Rd NH44, Namakkal 637003, Tamil Nadu, India; [Sowmya, V. L.] BMS Inst Technol & Management, Dept Artificial Intelligence & Machine Learning, Bengaluru 560119, India; [Alfurhood, Badria Sulaiman] Princess Nourah bint Abdulrahman Univ, Coll Comp & Informat Sci, Dept Comp Sci, POB 84428, Riyadh 11671, Saudi Arabia; [Irudayasamy, Amalraj] Univ Technol & Appl Sci, Coll Comp & Informat Sci, Dept Comp & Informat Sci, Nizwa 611, Oman; [Natarajan, Rajesh] Univ Technol & Appl Sci, Coll Comp & Informat Sci, Dept Comp & Informat Sci, AI Aqr 324, Shinas, Oman | R59: Bancos
A60: =IF(B60="","",ROW()-2) | B60: Transaction monitoring in anti-money laundering: A qualitative analysis and points of view from industry | C60: Oztas, B; Cetinkaya, D; Adedoyin, F; Budka, M; Aksu, G; Dogan, H | D60: 2024 | E60: Future Generation Computer Systems-The International Journal Of Escience | F60: 10.1016/j.future.2024.05.027 | G60: Financial institutions face significant challenges in their efforts to prevent money laundering and terrorist financing due to criminals' continuously evolving techniques and the vast volume of transactions that need to be processed. The traditional rules-based methods utilised in banks produce high false positive rates, which lead to increased costs and inefficiencies. This study identified the perspectives of 8 anti-money laundering (AML) specialists on the current state and potential improvements in transaction monitoring methods. The results provide in-depth knowledge of the problems and requirements for researchers and practitioners. Semi-structured interviews conducted with the AML experts (totalling 480 min) identified the challenges, requirements for successful implementation, and future trends in transaction monitoring. The findings reveal a growing interest in machine learning and artificial intelligence to enhance the efficiency and accuracy of current approaches. Furthermore, innovative methods such as graph analysis and anomaly detection were suggested to overcome the limitations of rule-based systems. Requirements such as explainability, flexibility, and identifying new risks were extracted and analysed. This research contributes to the existing literature by providing valuable insights from industry experts, guiding the development of advanced transaction monitoring methods, and addressing the disconnect and lack of studies between industries and academicians in the domain. | H60: Web of Science | I60: =IF(B60="","",IF(AND(F60<>"",SUMPRODUCT(--ISNUMBER(SEARCH(Preseleccionados!$A$2:$A$11,F60)))>0),"YA ESTÁ",IF(AND(F60<>"",COUNTIF($F$3:F60,F60)>1),"REPETIDO",""))) | J60: =IF(OR(B60="",I60<>""),"",IF(MOD(COUNTIFS($B$3:B60,"<>",$I$3:I60,""),2)=1,"Carlos","Joaquín")) | P60: =IF(J60="","",IF(K60="Sale","Descartado",IF(L60="Sale","Descartado",IF(OR(M60="Q3",M60="Q4",M60="No aparece"),"Descartado",IF(N60="Sale","Descartado",IF(O60="Sigue","APROBADO","En proceso")))))) | Q60: [Oztas, Berkan; Cetinkaya, Deniz; Adedoyin, Festus; Budka, Marcin; Dogan, Huseyin] Bournemouth Univ, Dept Comp & Informat, Talbot Campus, Bournemouth BH12 5BB, England; [Aksu, Gokhan] Danske Bank, London EC4N 7DT, England | R60: Bancos
A61: =IF(B61="","",ROW()-2) | B61: Automatic suppression of false positive alerts in anti-money laundering systems using machine learning | C61: Bakry, AN; Alsharkawy, AS; Farag, MS; Raslan, KR | D61: 2024 | E61: Journal Of Supercomputing | F61: 10.1007/s11227-023-05708-z | G61: Criminal activities generate an estimated $2 trillion in laundered money per year, highlighting the need for financial institutions to detect and report suspicious activity to protect their reputation. However, rule-based models commonly used for this purpose generate a high number of false positives, draining compliance team time, and increasing investigation costs. However, the application of machine learning in conjunction with rule-based models presents noteworthy implications, encompassing the potential reduction in false positives and the concomitant risk of machine learning inadvertently suppressing true positive alerts. This paper proposes a framework called automatic suppression based on XGBoost for anti-money laundering (ASXAML) to enhance detection by reducing false positives. ASXAML leverages recursive feature elimination with cross-validation for optimal feature selection. Subsequently, Optuna is employed to fine-tune hyperparameters for the XGBoost model. Results indicate that ASXAML achieves an optimal balance between reducing false positives and avoiding missed money laundering events, with an 86% F-beta score and only 11% money laundering customers were incorrectly closed out of 1926 in the test data. | H61: Web of Science | I61: =IF(B61="","",IF(AND(F61<>"",SUMPRODUCT(--ISNUMBER(SEARCH(Preseleccionados!$A$2:$A$11,F61)))>0),"YA ESTÁ",IF(AND(F61<>"",COUNTIF($F$3:F61,F61)>1),"REPETIDO",""))) | J61: =IF(OR(B61="",I61<>""),"",IF(MOD(COUNTIFS($B$3:B61,"<>",$I$3:I61,""),2)=1,"Carlos","Joaquín")) | P61: =IF(J61="","",IF(K61="Sale","Descartado",IF(L61="Sale","Descartado",IF(OR(M61="Q3",M61="Q4",M61="No aparece"),"Descartado",IF(N61="Sale","Descartado",IF(O61="Sigue","APROBADO","En proceso")))))) | Q61: [Bakry, Ahmed N.; Alsharkawy, Almohammady S.; Farag, Mohamed S.; Raslan, K. R.] Al Azhar Univ, Fac Sci, Dept Math, Nasr City, Cairo, Egypt | R61: Bancos
A62: =IF(B62="","",ROW()-2) | B62: Detection of abnormal transaction using spatial ontology-based deep learning approach | C62: Sambandam, P | D62: 2025 | E62: Knowledge And Information Systems | F62: 10.1007/s10115-025-02579-z | G62: Spatial ontology is one of the significant techniques for detecting suspicious transactions in financial institutions. This work proposes an expert system via spatial ontology-based Deep learning for effectively detecting abnormal transactions. The proposed methodology has the stages like pre-processing, construction of ontology and transaction detection. The initial step is pre-processing, during which specific data items are converted into ontology format and noisy data is eliminated. Next, a set of semantic web rule languages and a knowledge base are incorporated into the construction of ontology. New knowledge is gathered from the predefined rules using native reasoning to assist in ontology about every transaction. The proposed method uses a stacked autoencoder (SAE), a deep learning technique, to classify normal and abnormal transactions, and it is trained on the deduced knowledge base. After the classification process, the abnormal transaction list is provided to the query inferred to obtain different information from that list. The experimental analysis is carried out on the two benchmark datasets, synthetic financial and credit card datasets, and compared with the existing approaches. The accuracy obtained by the proposed model for synthetic financial and credit card datasets is 93% and 96.23%, respectively. The experimental results showed that the proposed system performed better than the state-of-the-art approaches. | H62: Web of Science | I62: =IF(B62="","",IF(AND(F62<>"",SUMPRODUCT(--ISNUMBER(SEARCH(Preseleccionados!$A$2:$A$11,F62)))>0),"YA ESTÁ",IF(AND(F62<>"",COUNTIF($F$3:F62,F62)>1),"REPETIDO",""))) | J62: =IF(OR(B62="",I62<>""),"",IF(MOD(COUNTIFS($B$3:B62,"<>",$I$3:I62,""),2)=1,"Carlos","Joaquín")) | P62: =IF(J62="","",IF(K62="Sale","Descartado",IF(L62="Sale","Descartado",IF(OR(M62="Q3",M62="Q4",M62="No aparece"),"Descartado",IF(N62="Sale","Descartado",IF(O62="Sigue","APROBADO","En proceso")))))) | Q62: [Sambandam, Palaniappan] Easwari Engn Coll, Dept Comp Sci & Business Syst, Chennai, Tamil Nadu, India | R62: Bancos
A63: =IF(B63="","",ROW()-2) | B63: Fund transfer fraud detection: Analyzing irregular transactions and customer with self-attention and neural networks | C63: Shih, YC; Dai, TS; Chen, YP; Ti, YW; Wang, WH; Kuo, Y | D63: 2025 | E63: Expert Systems With Applications | F63: 10.1016/j.eswa.2024.125211 | G63: This paper presents a method for identifying fraudulent fund transfers using real bank data, analyzing customer information, transactional activities, and customer relationships. The preprocessing step transforms high- dimensional, irregular transaction time series into regular time series, then further compresses them in a latent space using a self-attention-based autoencoder. To address the scarcity of fraudulent data samples and mitigate training issues caused by data imbalance, various deep generative models, including the conditional variational autoencoder and Wasserstein generative adversarial network, are applied to generate additional fraudulent raw data and augment fraud samples in latent space. The reparameterization trick is integrated into the encoder-decoder structure to boost the model's generative capabilities. Additionally, a Graph Neural Network (GNN) is used to model customer relationships. The proposed approach utilizes end-to-end learning, integrating the autoencoder's reconstruction loss, KL divergence loss (when reparameterization trick is applied), and classification loss for fraud detection. To optimize computational resources, neighborhood sampling for GNN is combined with mini-batch training for the autoencoder, improving both training efficiency and model reliability. Comprehensive experiments demonstrate the effectiveness of the proposed fusion network, highlighting the importance of each component and preprocessing step. For example, the areas under the precision-recall curves for fraud detection show notable improvements in our model. For suspicious transactions identified by the bank's rules, other models range from 0.66% to 22.15%, while our model reached 27%. For non-suspicious transactions, other models range from 2.53% to 22.00%, with our model achieving 22.90%. This model has potential for wider applications in anomaly detection, particularly in datasets with irregular time series and complex customer relationships. | H63: Web of Science | I63: =IF(B63="","",IF(AND(F63<>"",SUMPRODUCT(--ISNUMBER(SEARCH(Preseleccionados!$A$2:$A$11,F63)))>0),"YA ESTÁ",IF(AND(F63<>"",COUNTIF($F$3:F63,F63)>1),"REPETIDO",""))) | J63: =IF(OR(B63="",I63<>""),"",IF(MOD(COUNTIFS($B$3:B63,"<>",$I$3:I63,""),2)=1,"Carlos","Joaquín")) | P63: =IF(J63="","",IF(K63="Sale","Descartado",IF(L63="Sale","Descartado",IF(OR(M63="Q3",M63="Q4",M63="No aparece"),"Descartado",IF(N63="Sale","Descartado",IF(O63="Sigue","APROBADO","En proceso")))))) | Q63: [Shih, Yi-Cheng; Chen, Ying-Ping; Kuo, Yun] Yang Ming Chiao Tung Univ, Dept Comp Sci, 1001 Daxue Rd, Hsinchu 300093, Taiwan; [Dai, Tian-Shyr; Wang, Wun-Hao] Yang Ming Chiao Tung Univ, Dept Informat Management & Finance, 1001 Daxue Rd, Hsinchu 300093, Taiwan; [Dai, Tian-Shyr] Natl Chengchi Univ, Risk & Insurance Res Ctr, 64,Sec 2,Zhi Nan Rd, Taipei 11605, Taiwan; [Ti, Yen-Wu] Xiamen Ocean Vocat Coll, Sch Informat Engn, 61 Tiyu Rd, Xiamen 361012, Fujian, Peoples R China | R63: Bancos
A64: =IF(B64="","",ROW()-2) | B64: Explainable artificial intelligence models for detecting suspicious bank transactions | C64: Narasapuram, NK; Shah, SAA; Shiratuddin, MF; Sohel, F | D64: 2026 | E64: International Journal Of Machine Learning And Cybernetics | F64: 10.1007/s13042-026-02994-w | G64: Detecting financial crime is a complex challenge due to evolving criminal strategies and fragmented detection systems, particularly in the areas of money laundering and fraud. While it is easy to implement, traditional rule-based approaches lack adaptability to new threats, and machine learning models, though more effective, often function as opaque black boxes, limiting their practical use in regulated domains like banking, where interpretability and accountability are essential. This research presents a novel framework that combines intrinsic and post-hoc XAI techniques to detect suspicious bank transactions. Intrinsic methods provide model-inherent transparency, while post-hoc methods offer behavior-level explanations, enabling robust cross-verification of the model's decision logic. This dual-layered explainability supports both global understanding of the model and local interpretability for individual predictions. Experimental evaluation on synthetic datasets shows that the proposed framework achieves promising results, with F1 scores ranging from 0.54 to 0.63 for anti-money laundering (AML) detection and 0.66 to 0.78 for fraud detection, depending on the underlying model architecture. The use of explainability tools also enables the identification of key features shared across fraud and AML cases, revealing structural similarities. These insights demonstrate that a unified model can effectively capture both crime types, offering practical benefits for integrated financial crime risk management. By addressing the information silos caused by different regulatory frameworks and departmental responsibilities, this work supports the development of joint investigative systems and facilitates better communication between compliance teams. In addition, the explainable nature of the models helps satisfy regulatory scrutiny while improving investigator trust and decision support. The proposed approach contributes to the growing field of interpretable machine learning by providing a scalable, auditable, and regulator-friendly solution for detecting complex financial crimes. | H64: Web of Science | I64: =IF(B64="","",IF(AND(F64<>"",SUMPRODUCT(--ISNUMBER(SEARCH(Preseleccionados!$A$2:$A$11,F64)))>0),"YA ESTÁ",IF(AND(F64<>"",COUNTIF($F$3:F64,F64)>1),"REPETIDO",""))) | J64: =IF(OR(B64="",I64<>""),"",IF(MOD(COUNTIFS($B$3:B64,"<>",$I$3:I64,""),2)=1,"Carlos","Joaquín")) | P64: =IF(J64="","",IF(K64="Sale","Descartado",IF(L64="Sale","Descartado",IF(OR(M64="Q3",M64="Q4",M64="No aparece"),"Descartado",IF(N64="Sale","Descartado",IF(O64="Sigue","APROBADO","En proceso")))))) | Q64: [Narasapuram, Narasimha Kumar; Shiratuddin, Mohd Fairuz; Sohel, Ferdous] Murdoch Univ, Sch Informat Technol, 90 South St, Murdoch, WA 6150, Australia; [Shah, Syed Afaq Ali] Edith Cowan Univ, Sch Sci, Perth, WA, Australia | R64: Bancos
A65: =IF(B65="","",ROW()-2) | B65: Machine Learning and Network Analysis for Cross-Border Suspicious Transaction Detection: Evidence From the FinCEN Files | C65: Ejime, OM; Kosemani, A; Onyeorueka, SIE | D65: 2026 | E65: Ieee Access | F65: 10.1109/ACCESS.2026.3685103 | G65: Traditional rule-based anti-money-laundering (AML) systems raise far more alerts than humans can plausibly investigate. In the aftermath of the International Consortium of Investigative Journalists' FinCEN Files revelations, compliance teams and regulators have begun to ask whether a data-driven approach might allocate scarce attention more effectively. This study presents a holistic framework that combines descriptive statistics, time-series modelling, geospatial analysis, network science and machine-learning classification to analyse 4,507 aggregated transaction groups (more than 200,000 individual transaction records) from the FinCEN Files dataset. After cleaning and integrating the data, we explore the heavy-tailed distribution of suspicious amounts, identify temporal spikes linked to economic crises, map cross-border corridors between secrecy jurisdictions, quantify centrality in the bank-to-bank network, fit an ARIMA model to monthly volumes, and construct a risk-scoring system. Logistic regression, Random Forest and XGBoost models are benchmarked against unsupervised isolation and one-class support vector methods. Ensemble models achieve area-under-the-ROC-curve scores around 0.97-0.98, substantially outperforming rule-based or unsupervised baselines. Our results demonstrate that network metrics, particularly degree and betweenness centrality, and high-risk corridor indicators, are among the most important predictors of suspicious behaviour. We conclude by situating these findings within the emerging literature on graph neural networks and proposing avenues for continual learning, beneficial ownership integration and cross-institutional transferability. Overall, the work illustrates that a judicious blend of machine learning and network analysis can reduce false positives and support risk-based AML supervision. | H65: Web of Science | I65: =IF(B65="","",IF(AND(F65<>"",SUMPRODUCT(--ISNUMBER(SEARCH(Preseleccionados!$A$2:$A$11,F65)))>0),"YA ESTÁ",IF(AND(F65<>"",COUNTIF($F$3:F65,F65)>1),"REPETIDO",""))) | J65: =IF(OR(B65="",I65<>""),"",IF(MOD(COUNTIFS($B$3:B65,"<>",$I$3:I65,""),2)=1,"Carlos","Joaquín")) | P65: =IF(J65="","",IF(K65="Sale","Descartado",IF(L65="Sale","Descartado",IF(OR(M65="Q3",M65="Q4",M65="No aparece"),"Descartado",IF(N65="Sale","Descartado",IF(O65="Sigue","APROBADO","En proceso")))))) | Q65: [Ejime, Oghenefejiro M.; Onyeorueka, Shedrack Isioma Egede] Univ Salford, Salford Business Sch, Manchester, England; [Kosemani, Abiola] Univ Salford, Sch Sci Engn & Environm, Manchester, England | R65: Bancos
A66: =IF(B66="","",ROW()-2) | B66: Predicting money laundering sanctions using machine learning algorithms and artificial neural networks | C66: Lokanan, ME | D66: 2023 | E66: Applied Economics Letters | F66: 10.1080/13504851.2023.2176435 | G66: This article used machine learning (ML) and artificial neural network (ANN) algorithms to predict the likelihood of a country being sanctioned by the Basel Institute on Governance for not adhering to anti-money laundering (AML) standards. Data for this paper came from the Basel AML Index and the World Bank. The results showed that the logistic regression and support vector machine (SVM) classifiers had the highest performance and balanced accuracy scores in sanction prediction. Additionally, these two algorithms also had the highest precision, specificity, and F1 scores, indicating that they were robust in their predictions of money laundering sanctions. In contrast to the ML classifiers, the ANN model had the highest sensitivity and receiver operating characteristic scores for money laundering sanctions. The strongest predictors of sanctions are financial transparency, political and legal risks, unemployment rate, and money laundering and terrorist financing risks. These findings reinforce the potential practical applications of ML and ANN models in predicting sanctions. | H66: Web of Science | I66: =IF(B66="","",IF(AND(F66<>"",SUMPRODUCT(--ISNUMBER(SEARCH(Preseleccionados!$A$2:$A$11,F66)))>0),"YA ESTÁ",IF(AND(F66<>"",COUNTIF($F$3:F66,F66)>1),"REPETIDO",""))) | J66: =IF(OR(B66="",I66<>""),"",IF(MOD(COUNTIFS($B$3:B66,"<>",$I$3:I66,""),2)=1,"Carlos","Joaquín")) | P66: =IF(J66="","",IF(K66="Sale","Descartado",IF(L66="Sale","Descartado",IF(OR(M66="Q3",M66="Q4",M66="No aparece"),"Descartado",IF(N66="Sale","Descartado",IF(O66="Sigue","APROBADO","En proceso")))))) | Q66: [Lokanan, Mark E.] Royal Rd Univ, Fac Management, Victoria, BC, Canada; [Lokanan, Mark E.] Royal Rd Univ, Fac Management, 2005 Sooke Rd, Victoria, BC V9B 5Y2, Canada | R66: Bancos
A67: =IF(B67="","",ROW()-2) | B67: Scalable Semi-Supervised Graph Learning Techniques for Anti Money Laundering | C67: Karim, MR; Hermsen, F; Chala, SA; De Perthuis, P; Mandal, A | D67: 2024 | E67: Ieee Access | F67: 10.1109/ACCESS.2024.3383784 | G67: Money laundering is the process by which criminals move large sums of illicit money to hidden locations and integrate them as legal funds through existing financial services. The United Nations (UN) estimates that 2 to 5% of global GDP, which is approximately 0.8 to 2.0 trillion dollars, is laundered globally every year. Therefore, accurately identifying such globally alarming activities is crucial for enforcing anti-money laundering (AML) measures. Numerous techniques have been proposed to detect money laundering from transaction graphs of money transfers between bank accounts by analysing the structural and behavioural dynamics of their corresponding dense subgraphs. However, these techniques often do not consider that money laundering usually involves high-volume flows of funds through chains of bank accounts. Moreover, most AML approaches either result in lower detection accuracy or incur higher computational costs, making them less reliable and suitable for real financial systems. Consequently, only a fraction of money laundering activities can be detected and prevented. In this paper, we propose an efficient approach to AML by employing semi-supervised graph learning techniques on a large-scale financial transactional graph in both pipeline settings (i.e., graph embedding models are first trained to generate node embeddings that are combined with additional topological graph features to train binary classifiers) and end-to-end settings (i.e., node classification is performed by training SkipGCN, FastGCN, and EvolveGCN without requiring separate classifiers) to identify nodes involved in potential money laundering activities. We evaluate our approach on four datasets: AMLSim, Elliptic, IBM AML, and SynthAML, with a view to scalability and practicality for real financial systems. Further, we provide local (e.g., how money is laundered between nodes) and global (e.g., what factors contribute to money laundering) explanations of the predictions by highlighting the predominant factors in money laundering cases and elucidating the mechanisms of illicit fund transfers between nodes to enhance the interpretability and transparency of the AML models. Experimental results suggest that our approach is scalable and effective at detecting money laundering from real and synthetic transaction graphs. | H67: Web of Science | I67: =IF(B67="","",IF(AND(F67<>"",SUMPRODUCT(--ISNUMBER(SEARCH(Preseleccionados!$A$2:$A$11,F67)))>0),"YA ESTÁ",IF(AND(F67<>"",COUNTIF($F$3:F67,F67)>1),"REPETIDO",""))) | J67: =IF(OR(B67="",I67<>""),"",IF(MOD(COUNTIFS($B$3:B67,"<>",$I$3:I67,""),2)=1,"Carlos","Joaquín")) | P67: =IF(J67="","",IF(K67="Sale","Descartado",IF(L67="Sale","Descartado",IF(OR(M67="Q3",M67="Q4",M67="No aparece"),"Descartado",IF(N67="Sale","Descartado",IF(O67="Sigue","APROBADO","En proceso")))))) | Q67: [Karim, Md. Rezaul; Hermsen, Felix; Chala, Sisay Adugna] Rhein Westfal TH Aachen, Dept Informat Syst & Databases, D-52074 Aachen, Germany; [Karim, Md. Rezaul; Hermsen, Felix; Mandal, Avikarsha] Fraunhofer FIT, Dept Data Sci & Artificial Intelligence, D-53757 St Augustin, Germany; [Chala, Sisay Adugna] Ecole Normale Super ENS, F-75005 Paris, France; [De Perthuis, Paola] Cosmian, F-75008 Paris, France | R67: Bancos
... A76: =IF(B76="","",ROW()-2) | B76: Machine Learning and Network Analysis for Cross-Border Suspicious Transaction Detection: Evidence From the FinCEN Files | C76: O. M. Ejime; A. Kosemani; S. I. E. Onyeorueka | D76: 2026 | E76: IEEE Access | F76: 10.1109/ACCESS.2026.3685103 | G76: Traditional rule-based anti-money-laundering (AML) systems raise far more alerts than humans can plausibly investigate. In the aftermath of the International Consortium of Investigative Journalists’ FinCEN Files revelations, compliance teams and regulators have begun to ask whether a data-driven approach might allocate scarce attention more effectively. This study presents a holistic framework that combines descriptive statistics, time-series modelling, geospatial analysis, network science and machine-learning classification to analyse 4,507 aggregated transaction groups (more than 200,000 individual transaction records) from the FinCEN Files dataset. After cleaning and integrating the data, we explore the heavy-tailed distribution of suspicious amounts, identify temporal spikes linked to economic crises, map cross-border corridors between secrecy jurisdictions, quantify centrality in the bank-to-bank network, fit an ARIMA model to monthly volumes, and construct a risk-scoring system. Logistic regression, Random Forest and XGBoost models are benchmarked against unsupervised isolation and one-class support vector methods. Ensemble models achieve area-under-the-ROC-curve scores around 0.97–0.98, substantially outperforming rule-based or unsupervised baselines. Our results demonstrate that network metrics, particularly degree and betweenness centrality, and high-risk corridor indicators, are among the most important predictors of suspicious behaviour. We conclude by situating these findings within the emerging literature on graph neural networks and proposing avenues for continual learning, beneficial ownership integration and cross-institutional transferability. Overall, the work illustrates that a judicious blend of machine learning and network analysis can reduce false positives and support risk-based AML supervision. | H76: IEEE Xplore | I76: =IF(B76="","",IF(AND(F76<>"",SUMPRODUCT(--ISNUMBER(SEARCH(Preseleccionados!$A$2:$A$11,F76)))>0),"YA ESTÁ",IF(AND(F76<>"",COUNTIF($F$3:F76,F76)>1),"REPETIDO",""))) | J76: =IF(OR(B76="",I76<>""),"",IF(MOD(COUNTIFS($B$3:B76,"<>",$I$3:I76,""),2)=1,"Carlos","Joaquín")) | P76: =IF(J76="","",IF(K76="Sale","Descartado",IF(L76="Sale","Descartado",IF(OR(M76="Q3",M76="Q4",M76="No aparece"),"Descartado",IF(N76="Sale","Descartado",IF(O76="Sigue","APROBADO","En proceso")))))) | Q76: Salford Business School, University of Salford, Manchester, U.K.; School of Science, Engineering and Environment, University of Salford, Manchester, U.K.; Salford Business School, University of Salford, Manchester, U.K. | R76: Bancos
A77: =IF(B77="","",ROW()-2) | B77: Deep Learning Approaches for Anti-Money Laundering on Mobile Transactions: Review, Framework, and Directions | C77: J. Fan; L. Khin Shar; R. Zhang; Z. Liu; W. Yang; D. Niyato; K. -Y. Lam | D77: 2026 | E77: IEEE Internet of Things Journal | F77: 10.1109/JIOT.2026.3653434 | G77: Money laundering is a financial crime that obscures the origin of illicit funds, necessitating the development and enforcement of anti-money laundering (AML) policies by governments and organizations. The proliferation of mobile payment platforms and smart IoT devices has significantly complicated AML investigations. As payment networks become more interconnected, there is an increasing need for efficient real-time detection to process large volumes of transaction data on heterogeneous payment systems by different operators such as digital currencies, cryptocurrencies, and account-based payments. Most of these mobile payment networks are supported by connected devices, many of which are considered loT devices in the FinTech space that constantly generate data. Furthermore, the growing complexity and unpredictability of transaction patterns across these networks contribute to a higher incidence of false positives. While machine learning (ML) solutions have the potential to enhance detection efficiency, their application in AML faces unique challenges, such as addressing privacy concerns tied to sensitive financial data and managing the real-world constraint of limited data availability due to data regulations. Existing surveys in the AML literature broadly review ML approaches for money laundering detection, but they often lack an in-depth exploration of advanced deep learning techniques—an emerging field with significant potential. To address this gap, this article conducts a comprehensive review of deep learning solutions and the challenges associated with their use in AML. In addition, we propose a novel framework that applies the least-privilege principle by integrating ML techniques, codifying AML red flags, and employing account profiling to provide context for predictions and enable effective fraud detection under limited data availability. Specifically, our approach defines AML-relevant financial profile characteristics and risk indicators to contextualize transactions and assess their associated risks. The proposed context-risk-predict AML (CRP-AML) model demonstrates notable success, achieving an ${F}1$ score of 82.51% on the minority class and nearly doubling the performance of other pattern detection models when the proportion of money laundering records in the dataset drops as low as 0.0005. | H77: IEEE Xplore | I77: =IF(B77="","",IF(AND(F77<>"",SUMPRODUCT(--ISNUMBER(SEARCH(Preseleccionados!$A$2:$A$11,F77)))>0),"YA ESTÁ",IF(AND(F77<>"",COUNTIF($F$3:F77,F77)>1),"REPETIDO",""))) | J77: =IF(OR(B77="",I77<>""),"",IF(MOD(COUNTIFS($B$3:B77,"<>",$I$3:I77,""),2)=1,"Carlos","Joaquín")) | K77: Sale | P77: =IF(J77="","",IF(K77="Sale","Descartado",IF(L77="Sale","Descartado",IF(OR(M77="Q3",M77="Q4",M77="No aparece"),"Descartado",IF(N77="Sale","Descartado",IF(O77="Sigue","APROBADO","En proceso")))))) | Q77: School of Computer Science and Engineering, Nanyang Technological University, Jurong West, Singapore; School of Computing and Information Systems, Singapore Management University, Bras Basah, Singapore; School of Computer Science and Engineering, Nanyang Technological University, Jurong West, Singapore; School of Computer Science and Engineering, Nanyang Technological University, Jurong West, Singapore; School of Computer Science and Engineering, Nanyang Technological University, Jurong West, Singapore; School of Computer Science and Engineering, Nanyang Technological University, Jurong West, Singapore; School of Computer Science and Engineering, Nanyang Technological University, Jurong West, Singapore | R77: Bancos
A78: =IF(B78="","",ROW()-2) | B78: Enhancing Anti-Money Laundering Frameworks: An Application of Graph Neural Networks in Cryptocurrency Transaction Classification | C78: S. Ferretti; G. D’Angelo; V. Ghini | D78: 2025 | E78: IEEE Access | F78: 10.1109/ACCESS.2025.3552240 | G78: Cryptocurrency money laundering is a pressing issue, as it not only facilitates and hides criminal activities but also disrupts markets and the overall financial system. To respond this challenge, researchers are trying to develop robust Anti-Money Laundering (AML) frameworks. These efforts play a crucial role in promoting societal welfare by mitigating the impact of criminal activities. This paper explores the application of Graph Neural Networks (GNNs) for classifying Bitcoin transactions. The research specifically employs Graph Convolutional Networks (GCNs), Graph Attention Networks (GATs), the Chebyshev spatial convolutional neural networks, and GraphSAGE networks. Based on the dataset analysis, we experiment with different subsets of features. Our findings suggest that the use of Graph Neural Network convolutions, combined with a final linear layer and skip connections, allow for an improvement in the state-of-the-art results, especially when Chebyshev and GATv2 convolutions are used. | H78: IEEE Xplore | I78: =IF(B78="","",IF(AND(F78<>"",SUMPRODUCT(--ISNUMBER(SEARCH(Preseleccionados!$A$2:$A$11,F78)))>0),"YA ESTÁ",IF(AND(F78<>"",COUNTIF($F$3:F78,F78)>1),"REPETIDO",""))) | J78: =IF(OR(B78="",I78<>""),"",IF(MOD(COUNTIFS($B$3:B78,"<>",$I$3:I78,""),2)=1,"Carlos","Joaquín")) | P78: =IF(J78="","",IF(K78="Sale","Descartado",IF(L78="Sale","Descartado",IF(OR(M78="Q3",M78="Q4",M78="No aparece"),"Descartado",IF(N78="Sale","Descartado",IF(O78="Sigue","APROBADO","En proceso")))))) | Q78: Department of Computer Science and Engineering (DISI), University of Bologna, Bologna, Italy; Department of Computer Science and Engineering (DISI), University of Bologna, Bologna, Italy; Department of Computer Science and Engineering (DISI), University of Bologna, Bologna, Italy | R78: Bancos
A79: =IF(B79="","",ROW()-2) | B79: Scalable Semi-Supervised Graph Learning Techniques for Anti Money Laundering | C79: M. R. Karim; F. Hermsen; S. A. Chala; P. De Perthuis; A. Mandal | D79: 2024 | E79: IEEE Access | F79: 10.1109/ACCESS.2024.3383784 | G79: Money laundering is the process by which criminals move large sums of illicit money to hidden locations and integrate them as legal funds through existing financial services. The United Nations (UN) estimates that 2 to 5% of global GDP, which is approximately 0.8 to 2.0 trillion dollars, is laundered globally every year. Therefore, accurately identifying such globally alarming activities is crucial for enforcing anti-money laundering (AML) measures. Numerous techniques have been proposed to detect money laundering from transaction graphs of money transfers between bank accounts by analysing the structural and behavioural dynamics of their corresponding dense subgraphs. However, these techniques often do not consider that money laundering usually involves high-volume flows of funds through chains of bank accounts. Moreover, most AML approaches either result in lower detection accuracy or incur higher computational costs, making them less reliable and suitable for real financial systems. Consequently, only a fraction of money laundering activities can be detected and prevented. In this paper, we propose an efficient approach to AML by employing semi-supervised graph learning techniques on a large-scale financial transactional graph in both pipeline settings (i.e., graph embedding models are first trained to generate node embeddings that are combined with additional topological graph features to train binary classifiers) and end-to-end settings (i.e., node classification is performed by training SkipGCN, FastGCN, and EvolveGCN without requiring separate classifiers) to identify nodes involved in potential money laundering activities. We evaluate our approach on four datasets: AMLSim, Elliptic, IBM AML, and SynthAML, with a view to scalability and practicality for real financial systems. Further, we provide local (e.g., how money is laundered between nodes) and global (e.g., what factors contribute to money laundering) explanations of the predictions by highlighting the predominant factors in money laundering cases and elucidating the mechanisms of illicit fund transfers between nodes to enhance the interpretability and transparency of the AML models. Experimental results suggest that our approach is scalable and effective at detecting money laundering from real and synthetic transaction graphs. | H79: IEEE Xplore | I79: =IF(B79="","",IF(AND(F79<>"",SUMPRODUCT(--ISNUMBER(SEARCH(Preseleccionados!$A$2:$A$11,F79)))>0),"YA ESTÁ",IF(AND(F79<>"",COUNTIF($F$3:F79,F79)>1),"REPETIDO",""))) | J79: =IF(OR(B79="",I79<>""),"",IF(MOD(COUNTIFS($B$3:B79,"<>",$I$3:I79,""),2)=1,"Carlos","Joaquín")) | P79: =IF(J79="","",IF(K79="Sale","Descartado",IF(L79="Sale","Descartado",IF(OR(M79="Q3",M79="Q4",M79="No aparece"),"Descartado",IF(N79="Sale","Descartado",IF(O79="Sigue","APROBADO","En proceso")))))) | Q79: Information Systems and Databases, RWTH Aachen University, Aachen, Germany; Information Systems and Databases, RWTH Aachen University, Aachen, Germany; Information Systems and Databases, RWTH Aachen University, Aachen, Germany; École Normale Supérieure (ENS), Paris, France; Department of Data Science and Artificial Intelligence, Fraunhofer FIT, Sankt Augustin, Germany | R79: Bancos
A80: =IF(B80="","",ROW()-2) | B80: Anti-Money Laundering by Group-Aware Deep Graph Learning | C80: D. Cheng; Y. Ye; S. Xiang; Z. Ma; Y. Zhang; C. Jiang | D80: 2023 | E80: IEEE Transactions on Knowledge and Data Engineering | F80: 10.1109/TKDE.2023.3272396 | G80: Anti-money laundering (AML) is a classical data mining problem in finance applications. As well known, money laundering (ML) is critical to the effective operation of transnational and organized crime, which affects a country's economy, government, and social wellbeings. Financial services organizations facilitate the movement of money and have been enlisted by governments to assist with the detection and prevention of money laundering, which is a key tool in the fight to reduce crime and create sustainable economic development. In the application of AML, user identity and financial behavior data are widely used to detect laundering transactions. In recent years, an increasing number of money laundering activities have been conducted by organized criminal gangs while most existing works still treat the actions of each account as independent identity behavior without considering the group-level conspired interactions. Therefore, in this paper, we propose a group-aware deep graph learning-based approach for organized money-laundering detection. In particular, we design a community-centric encoder to represent the nodes and attributes in user transaction graphs and derive the adjacent gang behaviors. Then, we devise a scheme of local enhancement to accommodate nodes with similar transaction features, which are aggregated into gangs for downstream detection. Extensive experiments on the real-world dataset from one of the largest bank card alliances worldwide show that our proposed method outperforms state-of-the-art methods in both offline and online modes, showing the effectiveness of money laundering detection with group-aware deep graph learning. | H80: IEEE Xplore | I80: =IF(B80="","",IF(AND(F80<>"",SUMPRODUCT(--ISNUMBER(SEARCH(Preseleccionados!$A$2:$A$11,F80)))>0),"YA ESTÁ",IF(AND(F80<>"",COUNTIF($F$3:F80,F80)>1),"REPETIDO",""))) | J80: =IF(OR(B80="",I80<>""),"",IF(MOD(COUNTIFS($B$3:B80,"<>",$I$3:I80,""),2)=1,"Carlos","Joaquín")) | P80: =IF(J80="","",IF(K80="Sale","Descartado",IF(L80="Sale","Descartado",IF(OR(M80="Q3",M80="Q4",M80="No aparece"),"Descartado",IF(N80="Sale","Descartado",IF(O80="Sigue","APROBADO","En proceso")))))) | Q80: Department of Computer Science and Technology, Tongji University, Shanghai, China; Department of Computer Science and Technology, Tongji University, Shanghai, China; School of Computer and Information Engineering, Zhejiang Gongshang University, Hangzhou, China; Research and Development Center of Financial Safety, China UnionPay Company, Ltd., Shanghai, China; School of Computer and Information Engineering, Zhejiang Gongshang University, Hangzhou, China; Department of Computer Science and Technology, Tongji University, Shanghai, China | R80: Bancos
A81: =IF(B81="","",ROW()-2) | B81: SF-DynFinGC: Scale-Free Dynamic Graph Construction for Event-Driven Spatiotemporal Learning in Financial Anomaly Detection | C81: Y. Chen; H. Zhu; H. Xu; C. Yi; Z. Chen; D. Landa-Silva | D81: 2026 | E81: IEEE Transactions on Artificial Intelligence | F81: 10.1109/TAI.2026.3698049 | G81: Existing machine learning methods for financial anomaly detection (FAD) typically overlook the complex spatiotemporal interactions inherent in financial data, significantly limiting detection accuracy and interpretability. While graph-based approaches have shown promise in modeling relational structures, existing methods mainly rely on static or overly simplistic dynamic graph constructions, struggling to capture these complex spatiotemporal interactions. To address these limitations, we propose SF-DynFinGC, a novel dynamic graph construction framework specifically tailored for event-driven spatiotemporal learning in FAD. SF-DynFinGC integrates scale-free structural regularization with a decay-governed global Top-k edge selection strategy, effectively reflecting real-world hierarchical and dispersed financial network characteristics. Through dynamically evolving graph structures triggered by financial events rather than fixed intervals, SF-DynFinGC accommodates irregular temporal and spatial data distributions. Comprehensive experiments on various benchmark datasets demonstrate that SF-DynFinGC consistently achieves state-of-the-art performance across graph neural network (GNN) and traditional classifiers, significantly outperforming existing static and dynamic graph construction approaches. Structural analyses further reveal that SF-DynFinGC generates interpretable and appropriately sparse graphs, highlighting critical transactional relationships indicative of complex anomaly patterns. This study provides a robust and interpretable dynamic graph construction framework that enhances both detection accuracy and analytical transparency, thereby extending the practical applicability of graph-based methods in financial risk management. | H81: IEEE Xplore | I81: =IF(B81="","",IF(AND(F81<>"",SUMPRODUCT(--ISNUMBER(SEARCH(Preseleccionados!$A$2:$A$11,F81)))>0),"YA ESTÁ",IF(AND(F81<>"",COUNTIF($F$3:F81,F81)>1),"REPETIDO",""))) | J81: =IF(OR(B81="",I81<>""),"",IF(MOD(COUNTIFS($B$3:B81,"<>",$I$3:I81,""),2)=1,"Carlos","Joaquín")) | K81: Sigue | L81: Sigue | P81: =IF(J81="","",IF(K81="Sale","Descartado",IF(L81="Sale","Descartado",IF(OR(M81="Q3",M81="Q4",M81="No aparece"),"Descartado",IF(N81="Sale","Descartado",IF(O81="Sigue","APROBADO","En proceso")))))) | Q81: School of Computer Science, University of Nottingham Malaysia, Selangor, Malaysia; School of Medicine and Health, Harbin Institute of Technology, Harbin, China; Faculty of Computing, Harbin Institute of Technology, Harbin, China; School of Medicine and Health, Harbin Institute of Technology, Harbin, China; School of Computer Science, University of Nottingham Malaysia, Selangor, Malaysia; School of Computer Science, University of Nottingham, Nottingham, U.K. | R81: Bancos
A82: =IF(B82="","",ROW()-2) | B82: U.S.-U.K. PETs Prize Challenge: Anomaly Detection via Privacy-Enhanced Federated Learning | C82: H. Asif; S. Min; X. Wang; J. Vaidya | D82: 2024 | E82: IEEE Transactions on Privacy | F82: 10.1109/TP.2024.3392721 | G82: Privacy Enhancing Technologies (PETs) have the potential to enable collaborative analytics without compromising privacy. This is extremely important for collaborative analytics can allow us to really extract value from the large amounts of data that are collected in domains such as healthcare, finance, and national security, among others. In order to foster innovation and move PETs from the research labs to actual deployment, the U.S. and U.K. governments partnered together in 2021 to propose the PETs prize challenge asking for privacy-enhancing solutions for two of the biggest problems facing us today: financial crime prevention and pandemic response. This article presents the Rutgers ScarletPets privacy-preserving federated learning approach to identify anomalous financial transactions in a payment network system (PNS). This approach utilizes a two-step anomaly detection methodology to solve the problem. In the first step, features are mined based on account-level data and labels, and then a privacy-preserving encoding scheme is used to augment these features to the data held by the PNS. In the second step, the PNS learns a highly accurate classifier from the augmented data. Our proposed approach has two major advantages: 1) there is no noteworthy drop in accuracy between the federated and the centralized setting, and 2) our approach is flexible since the PNS can keep improving its model and features to build a better classifier without imposing any additional computational or privacy burden on the banks. Notably, our solution won the first prize in the US for its privacy, utility, efficiency, and flexibility. | H82: IEEE Xplore | I82: =IF(B82="","",IF(AND(F82<>"",SUMPRODUCT(--ISNUMBER(SEARCH(Preseleccionados!$A$2:$A$11,F82)))>0),"YA ESTÁ",IF(AND(F82<>"",COUNTIF($F$3:F82,F82)>1),"REPETIDO",""))) | J82: =IF(OR(B82="",I82<>""),"",IF(MOD(COUNTIFS($B$3:B82,"<>",$I$3:I82,""),2)=1,"Carlos","Joaquín")) | P82: =IF(J82="","",IF(K82="Sale","Descartado",IF(L82="Sale","Descartado",IF(OR(M82="Q3",M82="Q4",M82="No aparece"),"Descartado",IF(N82="Sale","Descartado",IF(O82="Sigue","APROBADO","En proceso")))))) | Q82: Information Systems and Business Analytics Department, Hofstra University, Hempstead, NY, USA; Management Science and Information Systems Department, Rutgers University, Newark, NJ, USA; Management Science and Information Systems Department, Rutgers University, Newark, NJ, USA; Management Science and Information Systems Department, Rutgers University, Newark, NJ, USA | R82: Bancos
A83: =IF(B83="","",ROW()-2) | B83: Regulatable and Privacy-Preserving Blockchain via Anomaly Detection on Private Transactions | C83: L. Yi; J. Liu; Z. Wan; K. Ren; C. Chen | D83: 2025 | E83: IEEE Transactions on Information Forensics and Security | F83: 10.1109/TIFS.2025.3628110 | G83: The recent popularity of cryptocurrencies like Bitcoin and Ethereum has drawn widespread attention to the blockchain technique. In particular, some private cryptocurrencies like Zerocash and Monero enhance privacy protection by concealing the identities of participants and transaction amounts. However, such comprehensive privacy measures present regulatory challenges to malicious activities like money laundering and extortion. Therefore, building a novel blockchain that maintains privacy while supporting regulatory oversight is crucial. In this paper, we propose a regulatable and privacy-preserving blockchain scheme that introduces a decoupled and preparatory regulatory process. It serves as a privacy-preserving first line of defense, enabling the identification of anomalous transactions without compromising the confidentiality of the underlying data. Our approach pioneers a method for anomaly screening on private transactions, mitigating risks without resorting to key escrow or content recovery, thus preserving end-to-end privacy for legitimate users. Initially, we explore suitable transaction features within private blockchains for training machine learning classifiers to detect anomalous behaviors. Subsequently, we customize a privacy-centric classifier employing homomorphic encryption to achieve private computation of anomaly detection without leaking sensitive information from private transaction content. We then construct the zero-knowledge proof for validating the encrypted computation process. Our work pioneers in fully integrating homomorphic encryption with zero-knowledge proof, enabling credible and trustworthy verification of the homomorphic ciphertext computations. Finally, we conduct comprehensive security analysis and experimental simulations. The experimental results demonstrate the efficiency and scalability of our approach. | H83: IEEE Xplore | I83: =IF(B83="","",IF(AND(F83<>"",SUMPRODUCT(--ISNUMBER(SEARCH(Preseleccionados!$A$2:$A$11,F83)))>0),"YA ESTÁ",IF(AND(F83<>"",COUNTIF($F$3:F83,F83)>1),"REPETIDO",""))) | J83: =IF(OR(B83="",I83<>""),"",IF(MOD(COUNTIFS($B$3:B83,"<>",$I$3:I83,""),2)=1,"Carlos","Joaquín")) | K83: Sale | P83: =IF(J83="","",IF(K83="Sale","Descartado",IF(L83="Sale","Descartado",IF(OR(M83="Q3",M83="Q4",M83="No aparece"),"Descartado",IF(N83="Sale","Descartado",IF(O83="Sigue","APROBADO","En proceso")))))) | Q83: Zhejiang University, Hangzhou, Zhejiang, China; Zhejiang University, Hangzhou, Zhejiang, China; Zhejiang Lab, Hangzhou, Zhejiang, China; Zhejiang University, Hangzhou, Zhejiang, China; Zhejiang University, Hangzhou, Zhejiang, China | R83: Bancos
A84: =IF(B84="","",ROW()-2) | B84: GAPLG: Graph Augmented With Pseudolabels Generation for Blockchain Anomaly Transaction Detection | C84: J. Huang; K. Bu; H. Han; B. Gong; A. Xiong; W. Wang; Q. Wu | D84: 2025 | E84: IEEE Transactions on Computational Social Systems | F84: 10.1109/TCSS.2025.3555658 | G84: Cryptocurrencies, underpinned by blockchain technology, face persistent threats such as money laundering and extortion due to their decentralized and anonymous nature. Detecting fraudulent transactions is crucial for ensuring the security of blockchain systems. However, the existing detection methods face the following challenges: lack of labeled data, severe class imbalance in labeled data, complex network structure, numerous parameters, and long training time. To address these challenges, we propose a novel semisupervised learning framework that combines the graph augmented with pseudolabels generation (GAPLG) model and postprocessing technique. Our framework employs graph learning networks to elucidate relationships between transactions and users. By utilizing pseudolabels for unlabeled transaction data and embedding them onto diverse graph nodes, we achieve precise labels, enhancing prediction accuracy. Additionally, we employ specific postprocessing technique, such as correction and smoothing (C&S) technology, to rectify residuals and refine labels, ensuring our framework rivals the best parameter and baseline models. Our method boasts high scalability and flexibility, aiding in optimizing various evaluation indicators. Experimental verification through multiple real transaction datasets under varying data segmentations, demonstrated its effectiveness when compared with other representative frameworks. The analysis validates the effectiveness and benefits of our method. | H84: IEEE Xplore | I84: =IF(B84="","",IF(AND(F84<>"",SUMPRODUCT(--ISNUMBER(SEARCH(Preseleccionados!$A$2:$A$11,F84)))>0),"YA ESTÁ",IF(AND(F84<>"",COUNTIF($F$3:F84,F84)>1),"REPETIDO",""))) | J84: =IF(OR(B84="",I84<>""),"",IF(MOD(COUNTIFS($B$3:B84,"<>",$I$3:I84,""),2)=1,"Carlos","Joaquín")) | P84: =IF(J84="","",IF(K84="Sale","Descartado",IF(L84="Sale","Descartado",IF(OR(M84="Q3",M84="Q4",M84="No aparece"),"Descartado",IF(N84="Sale","Descartado",IF(O84="Sigue","APROBADO","En proceso")))))) | Q84: Faculty of Information Technology, Beijing University of Technology, Beijing, China; Faculty of Information Technology, Beijing University of Technology, Beijing, China; Faculty of Information Technology, Beijing University of Technology, Beijing, China; Faculty of Information Technology, Beijing University of Technology, Beijing, China; State Key Laboratory of Networking and Switching Technology, Beijing University of Posts and Telecommunications, Beijing, China; College of Electronic and Information Engineering, Nanjing University of Aeronautics and Astronautics, Nanjing, China; College of Electronic and Information Engineering, Nanjing University of Aeronautics and Astronautics, Nanjing, China | R84: Bancos
